{
	"Id": "Lootable_00518",
	"IsStatic": true,
	"useGravity": true,
	"randomRotation": false,
	"Position": {
		"x": 0,
		"y": 0,
		"z": 0
	},
	"Rotation": {
		"x": 0,
		"y": 0,
		"z": 0
	},
	"IsGroupPosition": false,
	"GroupPositions": [],
	"Root": "5e06761596074431445d4f05",
	"Items": [
		{
			"_id": "5e06761596074431445d4f05",
			"_tpl": "5909d7cf86f77470ee57d75a"
		},
		{
			"_id": "5e06761596074431445d4f06",
			"_tpl": "59e6449086f7746c9f75e822",
			"parentId": "5e06761596074431445d4f05",
			"slotId": "main",
			"location": {
				"x": 0,
				"y": 0,
				"r": 0
			}
		},
		{
			"_id": "5e06761596074431445d4f07",
			"_tpl": "578395402459774a256959b5",
			"parentId": "5e06761596074431445d4f05",
			"slotId": "main",
			"location": {
				"x": 2,
				"y": 0,
				"r": 0
			}
		}
	]
}