{
	"Id": "Lootable_00003",
	"IsStatic": true,
	"useGravity": true,
	"randomRotation": false,
	"Position": {
		"x": 0,
		"y": 0,
		"z": 0
	},
	"Rotation": {
		"x": 0,
		"y": 0,
		"z": 0
	},
	"IsGroupPosition": false,
	"GroupPositions": [],
	"Root": "5e0675779a5d683c327ecbb9",
	"Items": [
		{
			"_id": "5e0675779a5d683c327ecbb9",
			"_tpl": "578f87b7245977356274f2cd"
		},
		{
			"_id": "5e0675779a5d683c327ecbba",
			"_tpl": "57347cd0245977445a2d6ff1",
			"parentId": "5e0675779a5d683c327ecbb9",
			"slotId": "main",
			"location": {
				"x": 0,
				"y": 0,
				"r": 0
			}
		},
		{
			"_id": "5e0675779a5d683c327ecbbb",
			"_tpl": "57347b8b24597737dd42e192",
			"parentId": "5e0675779a5d683c327ecbb9",
			"slotId": "main",
			"location": {
				"x": 1,
				"y": 0,
				"r": 0
			}
		}
	]
}