{
	"items": [
		{
			"_id": "5c6687d65e9d882c8841f0fd",
			"_tpl": "55d7217a4bdc2d86028b456d"
		},
		{
			"_id": "5c6687d65e9d882c8841f121",
			"_tpl": "557ffd194bdc2d28148b457f",
			"parentId": "5c6687d65e9d882c8841f0fd",
			"slotId": "Pockets"
		},
		{
			"_id": "5c6687d65e9d882c8841f0fc",
			"_tpl": "566abbc34bdc2d92178b4576"
		},
		{
			"_id": "5c6687d65e9d882c8841f0ff",
			"_tpl": "5963866b86f7747bfa1c4462"
		},
		{
			"_id": "5c6687d65e9d882c8841f0fe",
			"_tpl": "5963866286f7747bf429b572"
		},
		{
			"_id": "TacticalVest923532",
			"_tpl": "5d5d85c586f774279a21cbdb",
			"parentId": "5c6687d65e9d882c8841f0fd",
			"slotId": "TacticalVest"
		},
		{
			"_id": "I21007219422797693LVXFMe",
			"_tpl": "583990e32459771419544dd2",
			"parentId": "5c6687d65e9d882c8841f0fd",
			"slotId": "FirstPrimaryWeapon"
		},
		{
			"_id": "I210072131582560693Ipu7L",
			"_tpl": "5649ad3f4bdc2df8348b4585",
			"parentId": "I21007219422797693LVXFMe",
			"slotId": "mod_pistol_grip"
		},
		{
			"_id": "I21007214617119510LSCUKg",
			"_tpl": "57dc347d245977596754e7a1",
			"parentId": "I21007219422797693LVXFMe",
			"slotId": "mod_stock"
		},
		{
			"_id": "MagazineWeaponScav4748",
			"_tpl": "55d4837c4bdc2d1d4e8b456c",
			"parentId": "I21007219422797693LVXFMe",
			"slotId": "mod_magazine"
		},
		{
			"_id": "AmmoMag18895",
			"_tpl": "56dff338d2720bbd668b4569",
			"parentId": "MagazineWeaponScav4748",
			"slotId": "cartridges",
			"upd": {
				"StackObjectsCount": 10
			}
		},
		{
			"_id": "I210072145191265578FMLPB",
			"_tpl": "57dc324a24597759501edc20",
			"parentId": "I21007219422797693LVXFMe",
			"slotId": "mod_muzzle"
		},
		{
			"_id": "I21007214647949498aOt20D",
			"_tpl": "57dc334d245977597164366f",
			"parentId": "I21007219422797693LVXFMe",
			"slotId": "mod_reciever"
		},
		{
			"_id": "I21007215360212556S2RvyG",
			"_tpl": "59d36a0086f7747e673f3946",
			"parentId": "I21007219422797693LVXFMe",
			"slotId": "mod_gas_block"
		},
		{
			"_id": "I210072166375059758aOdfm",
			"_tpl": "56dfef82d2720bbd668b4567",
			"parentId": "I210072161733312651r0JD0",
			"slotId": "cartridges",
			"location": 0,
			"upd": {
				"StackObjectsCount": 30
			}
		},
		{
			"_id": "I21007217038488842AGmbED",
			"_tpl": "57dc32dc245977596d4ef3d3",
			"parentId": "I21007215360212556S2RvyG",
			"slotId": "mod_handguard"
		},
		{
			"_id": "FuckYouUnlimitedAmmo115084",
			"_tpl": "5857a8bc2459772bad15db29",
			"parentId": "5c6687d65e9d882c8841f0fd",
			"slotId": "SecuredContainer"
		},
		{
			"_id": "iHateThatShit264601",
			"_tpl": "56dff338d2720bbd668b4569",
			"parentId": "FuckYouUnlimitedAmmo115084",
			"slotId": "main",
			"upd": {
				"StackObjectsCount": 60
			}
		},
		{
			"_id": "iHateThatShit466443",
			"_tpl": "56dff061d2720bb5668b4567",
			"parentId": "FuckYouUnlimitedAmmo115084",
			"slotId": "main",
			"upd": {
				"StackObjectsCount": 60
			}
		},
		{
			"_id": "iHateThatShit371958",
			"_tpl": "56dff026d2720bb8668b4567",
			"parentId": "FuckYouUnlimitedAmmo115084",
			"slotId": "main",
			"upd": {
				"StackObjectsCount": 60
			}
		},
		{
			"_id": "iHateThatShit413084",
			"_tpl": "56dff338d2720bbd668b4569",
			"parentId": "FuckYouUnlimitedAmmo115084",
			"slotId": "main",
			"upd": {
				"StackObjectsCount": 60
			}
		},
		{
			"_id": "iHateThatShit176882",
			"_tpl": "56dff026d2720bb8668b4567",
			"parentId": "FuckYouUnlimitedAmmo115084",
			"slotId": "main",
			"upd": {
				"StackObjectsCount": 60
			}
		},
		{
			"_id": "iHateThatShit29835",
			"_tpl": "56dff216d2720bbd668b4568",
			"parentId": "FuckYouUnlimitedAmmo115084",
			"slotId": "main",
			"upd": {
				"StackObjectsCount": 60
			}
		},
		{
			"_id": "iHateThatShit557466",
			"_tpl": "56dff3afd2720bba668b4567",
			"parentId": "FuckYouUnlimitedAmmo115084",
			"slotId": "main",
			"upd": {
				"StackObjectsCount": 60
			}
		},
		{
			"_id": "iHateThatShit579801",
			"_tpl": "56dff216d2720bbd668b4568",
			"parentId": "FuckYouUnlimitedAmmo115084",
			"slotId": "main",
			"upd": {
				"StackObjectsCount": 60
			}
		},
		{
			"_id": "iHateThatShit4461",
			"_tpl": "56dff4ecd2720b5f5a8b4568",
			"parentId": "FuckYouUnlimitedAmmo115084",
			"slotId": "main",
			"upd": {
				"StackObjectsCount": 60
			}
		},
		{
			"_id": "mag0Vest796872",
			"_tpl": "55d4837c4bdc2d1d4e8b456c",
			"parentId": "TacticalVest923532",
			"slotId": "1",
			"location": {
				"x": 0,
				"y": 1,
				"r": "Horizontal"
			}
		},
		{
			"_id": "AmmoMag0Vest758390",
			"_tpl": "56dff026d2720bb8668b4567",
			"parentId": "mag0Vest796872",
			"slotId": "cartridges",
			"upd": {
				"StackObjectsCount": 10
			}
		},
		{
			"_id": "mag1Vest951824",
			"_tpl": "55d4837c4bdc2d1d4e8b456c",
			"parentId": "TacticalVest923532",
			"slotId": "3",
			"location": {
				"x": 0,
				"y": 0,
				"r": "Horizontal"
			}
		},
		{
			"_id": "AmmoMag1Vest961178",
			"_tpl": "56dff338d2720bbd668b4569",
			"parentId": "mag1Vest951824",
			"slotId": "cartridges",
			"upd": {
				"StackObjectsCount": 10
			}
		},
		{
			"_id": "mag2Vest215240",
			"_tpl": "55d4837c4bdc2d1d4e8b456c",
			"parentId": "TacticalVest923532",
			"slotId": "5",
			"location": {
				"x": 0,
				"y": 0,
				"r": "Horizontal"
			}
		},
		{
			"_id": "AmmoMag2Vest721062",
			"_tpl": "56dff4a2d2720bbd668b456a",
			"parentId": "mag2Vest215240",
			"slotId": "cartridges",
			"upd": {
				"StackObjectsCount": 10
			}
		},
		{
			"_id": "mag2Vest868762",
			"_tpl": "55d4837c4bdc2d1d4e8b456c",
			"parentId": "TacticalVest923532",
			"slotId": "5",
			"location": {
				"x": 0,
				"y": 1,
				"r": "Horizontal"
			}
		},
		{
			"_id": "AmmoMag2Vest587536",
			"_tpl": "56dff061d2720bb5668b4567",
			"parentId": "mag2Vest868762",
			"slotId": "cartridges",
			"upd": {
				"StackObjectsCount": 10
			}
		},
		{
			"_id": "Scabbard489199",
			"_tpl": "57e26fc7245977162a14b800",
			"parentId": "5c6687d65e9d882c8841f0fd",
			"slotId": "Scabbard"
		},
		{
			"_id": "Headwear402146",
			"_tpl": "5aa2b87de5b5b00016327c25",
			"parentId": "5c6687d65e9d882c8841f0fd",
			"slotId": "Headwear"
		},
		{
			"_id": "FaceCover394832",
			"_tpl": "572b7fa524597762b747ce82",
			"parentId": "5c6687d65e9d882c8841f0fd",
			"slotId": "FaceCover"
		},
		{
			"_id": "Backpack494023",
			"_tpl": "56e33634d2720bd8058b456b",
			"parentId": "5c6687d65e9d882c8841f0fd",
			"slotId": "Backpack"
		},
		{
			"_id": "BP_Backpack494023_466168",
			"_tpl": "5c1d0dc586f7744baf2e7b79",
			"parentId": "Backpack494023",
			"slotId": "main",
			"location": {
				"x": 0,
				"y": 0,
				"r": "Horizontal"
			}
		},
		{
			"_id": "BP_Backpack494023_898919",
			"_tpl": "5d1c774f86f7746d6620f8db",
			"parentId": "Backpack494023",
			"slotId": "main",
			"location": {
				"x": 0,
				"y": 1,
				"r": "Horizontal"
			}
		},
		{
			"_id": "BP_Backpack494023_599511",
			"_tpl": "57347baf24597738002c6178",
			"parentId": "Backpack494023",
			"slotId": "main",
			"location": {
				"x": 0,
				"y": 2,
				"r": "Horizontal"
			}
		},
		{
			"_id": "BP_Backpack494023_819333",
			"_tpl": "5734758f24597738025ee253",
			"parentId": "Backpack494023",
			"slotId": "main",
			"location": {
				"x": 1,
				"y": 0,
				"r": "Horizontal"
			}
		},
		{
			"_id": "BP_Backpack494023_205249",
			"_tpl": "5d1b304286f774253763a528",
			"parentId": "Backpack494023",
			"slotId": "main",
			"location": {
				"x": 1,
				"y": 1,
				"r": "Horizontal"
			}
		},
		{
			"_id": "BP_Backpack494023_549348",
			"_tpl": "5d1b31ce86f7742523398394",
			"parentId": "Backpack494023",
			"slotId": "main",
			"location": {
				"x": 2,
				"y": 0,
				"r": "Horizontal"
			}
		},
		{
			"_id": "BP_Backpack494023_786268",
			"_tpl": "544fb62a4bdc2dfb738b4568",
			"parentId": "Backpack494023",
			"slotId": "main",
			"location": {
				"x": 2,
				"y": 1,
				"r": "Horizontal"
			}
		},
		{
			"_id": "BP_Backpack494023_108761",
			"_tpl": "5d40407c86f774318526545a",
			"parentId": "Backpack494023",
			"slotId": "main",
			"location": {
				"x": 3,
				"y": 0,
				"r": "Horizontal"
			}
		},
		{
			"_id": "ArmorVest811762",
			"_tpl": "5ab8e79e86f7742d8b372e78",
			"parentId": "5c6687d65e9d882c8841f0fd",
			"slotId": "ArmorVest",
			"upd": {
				"Repairable": {
					"MaxDurability": 65,
					"Durability": 6
				}
			}
		},
		{
			"_id": "Pocket_526205",
			"_tpl": "59e366c186f7741778269d85",
			"parentId": "5c6687d65e9d882c8841f121",
			"slotId": "pocket1",
			"location": {
				"x": 0,
				"y": 0,
				"r": "Horizontal"
			},
			"upd": {
				"SpawnedInSession": true
			}
		},
		{
			"_id": "Pocket_611497",
			"_tpl": "5e2af29386f7746d4159f077",
			"parentId": "5c6687d65e9d882c8841f121",
			"slotId": "pocket2",
			"location": {
				"x": 0,
				"y": 0,
				"r": "Horizontal"
			},
			"upd": {
				"SpawnedInSession": true
			}
		},
		{
			"_id": "Pocket_951768",
			"_tpl": "5a0eecf686f7740350630097",
			"parentId": "5c6687d65e9d882c8841f121",
			"slotId": "pocket3",
			"location": {
				"x": 0,
				"y": 0,
				"r": "Horizontal"
			},
			"upd": {
				"SpawnedInSession": true
			}
		}
	],
	"equipment": "5c6687d65e9d882c8841f0fd",
	"stash": "5c6687d65e9d882c8841f0fc",
	"questRaidItems": "5c6687d65e9d882c8841f0fe",
	"questStashItems": "5c6687d65e9d882c8841f0ff",
	"fastPanel": {}
}