{
	"items": [
		{
			"_id": "5c6687d65e9d882c8841f0fd",
			"_tpl": "55d7217a4bdc2d86028b456d"
		},
		{
			"_id": "5c6687d65e9d882c8841f121",
			"_tpl": "557ffd194bdc2d28148b457f",
			"parentId": "5c6687d65e9d882c8841f0fd",
			"slotId": "Pockets"
		},
		{
			"_id": "5c6687d65e9d882c8841f0fc",
			"_tpl": "566abbc34bdc2d92178b4576"
		},
		{
			"_id": "5c6687d65e9d882c8841f0ff",
			"_tpl": "5963866b86f7747bfa1c4462"
		},
		{
			"_id": "5c6687d65e9d882c8841f0fe",
			"_tpl": "5963866286f7747bf429b572"
		},
		{
			"_id": "TacticalVest504806",
			"_tpl": "5648a69d4bdc2ded0b8b457b",
			"parentId": "5c6687d65e9d882c8841f0fd",
			"slotId": "TacticalVest"
		},
		{
			"_id": "I331037216215836018jGtfq",
			"_tpl": "576165642459773c7a400233",
			"parentId": "5c6687d65e9d882c8841f0fd",
			"slotId": "FirstPrimaryWeapon"
		},
		{
			"_id": "I331037219561822274rTdbu",
			"_tpl": "576169e62459773c69055191",
			"parentId": "I331037216215836018jGtfq",
			"slotId": "mod_handguard"
		},
		{
			"_id": "I331037212680749283oTwUz",
			"_tpl": "576167ab2459773cad038c43",
			"parentId": "I331037216215836018jGtfq",
			"slotId": "mod_muzzle"
		},
		{
			"_id": "I331037214287133904UsXmw",
			"_tpl": "5649ade84bdc2d1b2b8b4587",
			"parentId": "I331037216215836018jGtfq",
			"slotId": "mod_pistol_grip"
		},
		{
			"_id": "I331037219819551362I4veV",
			"_tpl": "57a9b9ce2459770ee926038d",
			"parentId": "I331037216215836018jGtfq",
			"slotId": "mod_sight_rear",
			"upd": {
				"Sight": {
					"SelectedSightMode": 0
				}
			}
		},
		{
			"_id": "MagazineWeaponScav6533",
			"_tpl": "57616a9e2459773c7a400234",
			"parentId": "I331037216215836018jGtfq",
			"slotId": "mod_magazine"
		},
		{
			"_id": "AmmoMag18006",
			"_tpl": "5d6e68b3a4b9361bca7e50b5",
			"parentId": "MagazineWeaponScav6533",
			"slotId": "cartridges",
			"upd": {
				"StackObjectsCount": 5
			}
		},
		{
			"_id": "FuckYouUnlimitedAmmo897092",
			"_tpl": "5857a8bc2459772bad15db29",
			"parentId": "5c6687d65e9d882c8841f0fd",
			"slotId": "SecuredContainer"
		},
		{
			"_id": "iHateThatShit708520",
			"_tpl": "58820d1224597753c90aeb13",
			"parentId": "FuckYouUnlimitedAmmo897092",
			"slotId": "main",
			"upd": {
				"StackObjectsCount": 60
			}
		},
		{
			"_id": "iHateThatShit566475",
			"_tpl": "5d6e68dea4b9361bcc29e659",
			"parentId": "FuckYouUnlimitedAmmo897092",
			"slotId": "main",
			"upd": {
				"StackObjectsCount": 60
			}
		},
		{
			"_id": "iHateThatShit782003",
			"_tpl": "58820d1224597753c90aeb13",
			"parentId": "FuckYouUnlimitedAmmo897092",
			"slotId": "main",
			"upd": {
				"StackObjectsCount": 60
			}
		},
		{
			"_id": "iHateThatShit902683",
			"_tpl": "5d6e6911a4b9361bd5780d52",
			"parentId": "FuckYouUnlimitedAmmo897092",
			"slotId": "main",
			"upd": {
				"StackObjectsCount": 60
			}
		},
		{
			"_id": "iHateThatShit252983",
			"_tpl": "5d6e6869a4b9361c140bcfde",
			"parentId": "FuckYouUnlimitedAmmo897092",
			"slotId": "main",
			"upd": {
				"StackObjectsCount": 60
			}
		},
		{
			"_id": "iHateThatShit797765",
			"_tpl": "5d6e68e6a4b9361c140bcfe0",
			"parentId": "FuckYouUnlimitedAmmo897092",
			"slotId": "main",
			"upd": {
				"StackObjectsCount": 60
			}
		},
		{
			"_id": "iHateThatShit442732",
			"_tpl": "5d6e6869a4b9361c140bcfde",
			"parentId": "FuckYouUnlimitedAmmo897092",
			"slotId": "main",
			"upd": {
				"StackObjectsCount": 60
			}
		},
		{
			"_id": "iHateThatShit682319",
			"_tpl": "5d6e6772a4b936088465b17c",
			"parentId": "FuckYouUnlimitedAmmo897092",
			"slotId": "main",
			"upd": {
				"StackObjectsCount": 60
			}
		},
		{
			"_id": "iHateThatShit352170",
			"_tpl": "5d6e68e6a4b9361c140bcfe0",
			"parentId": "FuckYouUnlimitedAmmo897092",
			"slotId": "main",
			"upd": {
				"StackObjectsCount": 60
			}
		},
		{
			"_id": "mag0Vest500369",
			"_tpl": "57616a9e2459773c7a400234",
			"parentId": "TacticalVest504806",
			"slotId": "1",
			"location": {
				"x": 0,
				"y": 0,
				"r": "Horizontal"
			}
		},
		{
			"_id": "AmmoMag0Vest961474",
			"_tpl": "58820d1224597753c90aeb13",
			"parentId": "mag0Vest500369",
			"slotId": "cartridges",
			"upd": {
				"StackObjectsCount": 5
			}
		},
		{
			"_id": "mag2Vest451837",
			"_tpl": "57616a9e2459773c7a400234",
			"parentId": "TacticalVest504806",
			"slotId": "4",
			"location": {
				"x": 0,
				"y": 0,
				"r": "Horizontal"
			}
		},
		{
			"_id": "AmmoMag2Vest214308",
			"_tpl": "5c0d591486f7744c505b416f",
			"parentId": "mag2Vest451837",
			"slotId": "cartridges",
			"upd": {
				"StackObjectsCount": 5
			}
		},
		{
			"_id": "mag0Vest708276",
			"_tpl": "57616a9e2459773c7a400234",
			"parentId": "TacticalVest504806",
			"slotId": "5",
			"location": {
				"x": 0,
				"y": 0,
				"r": "Horizontal"
			}
		},
		{
			"_id": "AmmoMag0Vest994602",
			"_tpl": "5d6e6806a4b936088465b17e",
			"parentId": "mag0Vest708276",
			"slotId": "cartridges",
			"upd": {
				"StackObjectsCount": 5
			}
		},
		{
			"_id": "mag0Vest936626",
			"_tpl": "57616a9e2459773c7a400234",
			"parentId": "TacticalVest504806",
			"slotId": "5",
			"location": {
				"x": 1,
				"y": 0,
				"r": "Horizontal"
			}
		},
		{
			"_id": "AmmoMag0Vest558914",
			"_tpl": "58820d1224597753c90aeb13",
			"parentId": "mag0Vest936626",
			"slotId": "cartridges",
			"upd": {
				"StackObjectsCount": 5
			}
		},
		null,
		{
			"_id": "StackAmmo48414671972",
			"_tpl": "5d6e6911a4b9361bd5780d52",
			"parentId": "TacticalVest504806",
			"slotId": "9",
			"upd": {
				"StackObjectsCount": 19
			}
		},
		{
			"_id": "Scabbard658171",
			"_tpl": "57e26ea924597715ca604a09",
			"parentId": "5c6687d65e9d882c8841f0fd",
			"slotId": "Scabbard"
		},
		{
			"_id": "Headwear357788",
			"_tpl": "5aa2b8d7e5b5b00014028f4a",
			"parentId": "5c6687d65e9d882c8841f0fd",
			"slotId": "Headwear"
		},
		{
			"_id": "FaceCover980790",
			"_tpl": "5bd0716d86f774171822ef4b",
			"parentId": "5c6687d65e9d882c8841f0fd",
			"slotId": "FaceCover"
		},
		{
			"_id": "ArmorVest896328",
			"_tpl": "5ab8e79e86f7742d8b372e78",
			"parentId": "5c6687d65e9d882c8841f0fd",
			"slotId": "ArmorVest",
			"upd": {
				"Repairable": {
					"MaxDurability": 65,
					"Durability": 4
				}
			}
		},
		{
			"_id": "Pocket_949625",
			"_tpl": "5d1b39a386f774252339976f",
			"parentId": "5c6687d65e9d882c8841f121",
			"slotId": "pocket1",
			"location": {
				"x": 0,
				"y": 0,
				"r": "Horizontal"
			},
			"upd": {
				"SpawnedInSession": true
			}
		},
		{
			"_id": "Pocket_336203",
			"_tpl": "5913611c86f77479e0084092",
			"parentId": "5c6687d65e9d882c8841f121",
			"slotId": "pocket2",
			"location": {
				"x": 0,
				"y": 0,
				"r": "Horizontal"
			},
			"upd": {
				"SpawnedInSession": true
			}
		}
	],
	"equipment": "5c6687d65e9d882c8841f0fd",
	"stash": "5c6687d65e9d882c8841f0fc",
	"questRaidItems": "5c6687d65e9d882c8841f0fe",
	"questStashItems": "5c6687d65e9d882c8841f0ff",
	"fastPanel": {}
}