{
	"Id": "Loot_backpack (6)1686122",
	"IsStatic": false,
	"useGravity": false,
	"randomRotation": false,
	"Position": {
		"x": 26.3689728,
		"y": 8.335,
		"z": 37.01747
	},
	"Rotation": {
		"x": 283.7444,
		"y": 113.681511,
		"z": 18.2201462
	},
	"IsGroupPosition": false,
	"GroupPositions": [],
	"Root": "5db5d02c533aa77c477a5046",
	"Items": [
		{
			"_id": "5db5d02c533aa77c477a5046",
			"_tpl": "544a5cde4bdc2d39388b456b"
		},
		{
			"_id": "5db5d02c533aa77c477a5047",
			"_tpl": "5751496424597720a27126da",
			"parentId": "5db5d02c533aa77c477a5046",
			"slotId": "main",
			"location": {
				"x": 0,
				"y": 0,
				"r": 0
			}
		},
		{
			"_id": "5db5d02c533aa77c477a5048",
			"_tpl": "57372ebf2459776862260582",
			"parentId": "5db5d02c533aa77c477a5046",
			"slotId": "main",
			"location": {
				"x": 1,
				"y": 0,
				"r": 0
			}
		},
		{
			"_id": "5db5d02c533aa77c477a5049",
			"_tpl": "56dff3afd2720bba668b4567",
			"parentId": "5db5d02c533aa77c477a5048",
			"slotId": "cartridges",
			"upd": {
				"StackObjectsCount": 30
			}
		}
	]
}