{
	"items": [
		{
			"_id": "5c6687d65e9d882c8841f0fd",
			"_tpl": "55d7217a4bdc2d86028b456d"
		},
		{
			"_id": "5c6687d65e9d882c8841f121",
			"_tpl": "557ffd194bdc2d28148b457f",
			"parentId": "5c6687d65e9d882c8841f0fd",
			"slotId": "Pockets"
		},
		{
			"_id": "5c6687d65e9d882c8841f0fc",
			"_tpl": "566abbc34bdc2d92178b4576"
		},
		{
			"_id": "5c6687d65e9d882c8841f0ff",
			"_tpl": "5963866b86f7747bfa1c4462"
		},
		{
			"_id": "5c6687d65e9d882c8841f0fe",
			"_tpl": "5963866286f7747bf429b572"
		},
		{
			"_id": "TacticalVest458289",
			"_tpl": "592c2d1a86f7746dbe2af32a",
			"parentId": "5c6687d65e9d882c8841f0fd",
			"slotId": "TacticalVest",
			"upd": {
				"SpawnedInSession": true
			}
		},
		{
			"_id": "I1131224525515616964x88x",
			"_tpl": "5de7bd7bfd6b4e6e2276dc25",
			"parentId": "5c6687d65e9d882c8841f0fd",
			"slotId": "FirstPrimaryWeapon"
		},
		{
			"_id": "MagazineWeaponScav1626",
			"_tpl": "5de8eac42a78646d96665d91",
			"parentId": "I1131224525515616964x88x",
			"slotId": "mod_magazine",
			"upd": {
				"SpawnedInSession": true
			}
		},
		{
			"_id": "AmmoMag19260",
			"_tpl": "58864a4f2459770fcc257101",
			"parentId": "MagazineWeaponScav1626",
			"slotId": "cartridges",
			"upd": {
				"SpawnedInSession": true,
				"StackObjectsCount": 30
			}
		},
		{
			"_id": "62d134ff-7629-4537-9782-0602cf80c11f",
			"_tpl": "5de8f237bbaf010b10528a70",
			"parentId": "I1131224525515616964x88x",
			"slotId": "mod_muzzle",
			"upd": {
				"SpawnedInSession": true
			}
		},
		{
			"_id": "548ff3e4-3383-4900-8da4-f8027c70d4c6",
			"_tpl": "5de910da8b6c4240ba2651b5",
			"parentId": "I1131224525515616964x88x",
			"slotId": "mod_stock",
			"upd": {
				"SpawnedInSession": true
			}
		},
		{
			"_id": "34de0ea0-9e7f-47bf-837c-09f5f2f723f2",
			"_tpl": "5de8fbad2fbe23140d3ee9c4",
			"parentId": "I1131224525515616964x88x",
			"slotId": "mod_foregrip",
			"upd": {
				"SpawnedInSession": true
			}
		},
		{
			"_id": "c226a5e7-1694-4746-aa99-3c6df0902e5c",
			"_tpl": "5e0090f7e9dc277128008b93",
			"parentId": "I1131224525515616964x88x",
			"slotId": "mod_reciever",
			"upd": {
				"SpawnedInSession": true
			}
		},
		{
			"_id": "34b56bf3-0b48-454e-b4f4-964ede2753eb",
			"_tpl": "5de922d4b11454561e39239f",
			"parentId": "I1131224525515616964x88x",
			"slotId": "mod_charge",
			"upd": {
				"SpawnedInSession": true
			}
		},
		{
			"_id": "4756a412-6309-4943-9d81-9cfa160814bc",
			"_tpl": "5de8f2d5b74cd90030650c72",
			"parentId": "62d134ff-7629-4537-9782-0602cf80c11f",
			"slotId": "mod_muzzle",
			"upd": {
				"SpawnedInSession": true
			}
		},
		{
			"_id": "6b2f3357-cddf-4f90-9c58-f2a726f10710",
			"_tpl": "5d2da1e948f035477b1ce2ba",
			"parentId": "c226a5e7-1694-4746-aa99-3c6df0902e5c",
			"slotId": "mod_scope"
		},
		{
			"_id": "mag0Vest553374",
			"_tpl": "5de8eaadbbaf010b10528a6d",
			"parentId": "TacticalVest458289",
			"slotId": "6",
			"location": {
				"x": 0,
				"y": 0,
				"r": "Horizontal"
			},
			"upd": {
				"SpawnedInSession": true
			}
		},
		{
			"_id": "AmmoMag0Vest20223",
			"_tpl": "56d59d3ad2720bdb418b4577",
			"parentId": "mag0Vest553374",
			"slotId": "cartridges",
			"upd": {
				"SpawnedInSession": true,
				"StackObjectsCount": 25
			}
		},
		{
			"_id": "Scabbard903313",
			"_tpl": "57e26fc7245977162a14b800",
			"parentId": "5c6687d65e9d882c8841f0fd",
			"slotId": "Scabbard",
			"upd": {
				"SpawnedInSession": true
			}
		},
		{
			"_id": "Backpack473630",
			"_tpl": "56e335e4d2720b6c058b456d",
			"parentId": "5c6687d65e9d882c8841f0fd",
			"slotId": "Backpack",
			"upd": {
				"SpawnedInSession": true
			}
		},
		{
			"_id": "BP_Backpack473630_808524",
			"_tpl": "59136e1e86f774432f15d133",
			"parentId": "Backpack473630",
			"slotId": "main",
			"location": {
				"x": 0,
				"y": 0,
				"r": "Horizontal"
			},
			"upd": {
				"SpawnedInSession": true
			}
		},
		{
			"_id": "BP_Backpack473630_743410",
			"_tpl": "5649a2464bdc2d91118b45a8",
			"parentId": "Backpack473630",
			"slotId": "main",
			"location": {
				"x": 0,
				"y": 1,
				"r": "Horizontal"
			},
			"upd": {
				"SpawnedInSession": true
			}
		},
		{
			"_id": "BP_Backpack473630_280028",
			"_tpl": "5d024f5cd7ad1a04a067e91a",
			"parentId": "Backpack473630",
			"slotId": "main",
			"location": {
				"x": 0,
				"y": 2,
				"r": "Horizontal"
			},
			"upd": {
				"SpawnedInSession": true
			}
		},
		{
			"_id": "BP_Backpack473630_871916",
			"_tpl": "58d2664f86f7747fec5834f6",
			"parentId": "Backpack473630",
			"slotId": "main",
			"location": {
				"x": 0,
				"y": 3,
				"r": "Horizontal"
			},
			"upd": {
				"SpawnedInSession": true
			}
		},
		{
			"_id": "BP_Backpack473630_339688",
			"_tpl": "5937ee6486f77408994ba448",
			"parentId": "Backpack473630",
			"slotId": "main",
			"location": {
				"x": 0,
				"y": 4,
				"r": "Horizontal"
			},
			"upd": {
				"SpawnedInSession": true
			}
		},
		{
			"_id": "BP_Backpack473630_125302",
			"_tpl": "5beec8b20db834001961942a",
			"parentId": "Backpack473630",
			"slotId": "main",
			"location": {
				"x": 1,
				"y": 0,
				"r": "Horizontal"
			},
			"upd": {
				"SpawnedInSession": true
			}
		},
		{
			"_id": "BP_Backpack473630_671158",
			"_tpl": "5d40425986f7743185265461",
			"parentId": "Backpack473630",
			"slotId": "main",
			"location": {
				"x": 1,
				"y": 1,
				"r": "Horizontal"
			},
			"upd": {
				"SpawnedInSession": true
			}
		},
		{
			"_id": "BP_Backpack473630_632756",
			"_tpl": "5b1fa9ea5acfc40018633c0a",
			"parentId": "Backpack473630",
			"slotId": "main",
			"location": {
				"x": 1,
				"y": 2,
				"r": "Horizontal"
			},
			"upd": {
				"SpawnedInSession": true
			}
		},
		{
			"_id": "BP_Backpack473630_963190",
			"_tpl": "5bffcf7a0db83400232fea79",
			"parentId": "Backpack473630",
			"slotId": "main",
			"location": {
				"x": 1,
				"y": 3,
				"r": "Horizontal"
			},
			"upd": {
				"SpawnedInSession": true
			}
		},
		{
			"_id": "BP_Backpack473630_162506",
			"_tpl": "5b39f8db5acfc40016387a1b",
			"parentId": "Backpack473630",
			"slotId": "main",
			"location": {
				"x": 1,
				"y": 4,
				"r": "Horizontal"
			},
			"upd": {
				"SpawnedInSession": true
			}
		}
	],
	"equipment": "5c6687d65e9d882c8841f0fd",
	"stash": "5c6687d65e9d882c8841f0fc",
	"questRaidItems": "5c6687d65e9d882c8841f0fe",
	"questStashItems": "5c6687d65e9d882c8841f0ff",
	"fastPanel": {}
}