{
	"items": [
		{
			"_id": "5c6687d65e9d882c8841f0fd",
			"_tpl": "55d7217a4bdc2d86028b456d"
		},
		{
			"_id": "5c6687d65e9d882c8841f121",
			"_tpl": "557ffd194bdc2d28148b457f",
			"parentId": "5c6687d65e9d882c8841f0fd",
			"slotId": "Pockets"
		},
		{
			"_id": "5c6687d65e9d882c8841f0fc",
			"_tpl": "566abbc34bdc2d92178b4576"
		},
		{
			"_id": "5c6687d65e9d882c8841f0ff",
			"_tpl": "5963866b86f7747bfa1c4462"
		},
		{
			"_id": "5c6687d65e9d882c8841f0fe",
			"_tpl": "5963866286f7747bf429b572"
		},
		{
			"_id": "TacticalVest303972",
			"_tpl": "5c0e3eb886f7742015526062",
			"parentId": "5c6687d65e9d882c8841f0fd",
			"slotId": "TacticalVest"
		},
		{
			"_id": "I210148412756888173FiYPh",
			"_tpl": "5c501a4d2e221602b412b540",
			"parentId": "5c6687d65e9d882c8841f0fd",
			"slotId": "FirstPrimaryWeapon"
		},
		{
			"_id": "I210148419897529201YrV85",
			"_tpl": "5c5039be2e221602b177c9ff",
			"parentId": "I210148412756888173FiYPh",
			"slotId": "mod_gas_block"
		},
		{
			"_id": "I210148415979506664Iiy3h",
			"_tpl": "5c503d0a2e221602b542b7ef",
			"parentId": "I210148412756888173FiYPh",
			"slotId": "mod_reciever"
		},
		{
			"_id": "I2101484151817291971YdQc",
			"_tpl": "5649d9a14bdc2d79388b4580",
			"parentId": "I210148412756888173FiYPh",
			"slotId": "mod_sight_rear",
			"upd": {
				"Sight": {
					"SelectedSightMode": 0
				}
			}
		},
		{
			"_id": "I210148418009688219UJJdb",
			"_tpl": "5c503af12e221602b177ca02",
			"parentId": "I210148412756888173FiYPh",
			"slotId": "mod_stock"
		},
		{
			"_id": "MagazineWeaponScav538",
			"_tpl": "5c503ad32e2216398b5aada2",
			"parentId": "I210148412756888173FiYPh",
			"slotId": "mod_magazine"
		},
		{
			"_id": "AmmoMag11407",
			"_tpl": "5a608bf24f39f98ffc77720e",
			"parentId": "MagazineWeaponScav538",
			"slotId": "cartridges",
			"upd": {
				"StackObjectsCount": 10
			}
		},
		{
			"_id": "I210148416705204828DmL6y",
			"_tpl": "58d39d3d86f77445bb794ae7",
			"parentId": "I2101484151817291971YdQc",
			"slotId": "mod_scope"
		},
		{
			"_id": "I210148417272264849Cemfa",
			"_tpl": "58d399e486f77442e0016fe7",
			"parentId": "I210148416705204828DmL6y",
			"slotId": "mod_scope",
			"upd": {
				"Sight": {
					"SelectedSightMode": 0
				}
			}
		},
		{
			"_id": "mag2Vest717028",
			"_tpl": "5c503ac82e221602b21d6e9a",
			"parentId": "TacticalVest303972",
			"slotId": "3",
			"location": {
				"x": 0,
				"y": 1,
				"r": "Horizontal"
			}
		},
		{
			"_id": "AmmoMag2Vest46901",
			"_tpl": "5e023e6e34d52a55c3304f71",
			"parentId": "mag2Vest717028",
			"slotId": "cartridges",
			"upd": {
				"StackObjectsCount": 5
			}
		},
		{
			"_id": "StackAmmo9448992362",
			"_tpl": "5a608bf24f39f98ffc77720e",
			"parentId": "TacticalVest303972",
			"slotId": "5",
			"upd": {
				"StackObjectsCount": 39
			}
		},
		{
			"_id": "Scabbard635804",
			"_tpl": "57e26fc7245977162a14b800",
			"parentId": "5c6687d65e9d882c8841f0fd",
			"slotId": "Scabbard"
		},
		{
			"_id": "Headwear175912",
			"_tpl": "5c1a1e3f2e221602b66cc4c2",
			"parentId": "5c6687d65e9d882c8841f0fd",
			"slotId": "Headwear"
		},
		{
			"_id": "FaceCover92530",
			"_tpl": "59e7715586f7742ee5789605",
			"parentId": "5c6687d65e9d882c8841f0fd",
			"slotId": "FaceCover"
		},
		{
			"_id": "Backpack686421",
			"_tpl": "5b44c6ae86f7742d1627baea",
			"parentId": "5c6687d65e9d882c8841f0fd",
			"slotId": "Backpack"
		},
		{
			"_id": "BP_Backpack686421_737689",
			"_tpl": "59e3596386f774176c10a2a2",
			"parentId": "Backpack686421",
			"slotId": "main",
			"location": {
				"x": 0,
				"y": 0,
				"r": "Horizontal"
			}
		},
		{
			"_id": "BP_Backpack686421_921499",
			"_tpl": "5c5db5fc2e2216000f1b2842",
			"parentId": "Backpack686421",
			"slotId": "main",
			"location": {
				"x": 0,
				"y": 2,
				"r": "Horizontal"
			}
		},
		{
			"_id": "BP_Backpack686421_186074",
			"_tpl": "591383f186f7744a4c5edcf3",
			"parentId": "Backpack686421",
			"slotId": "main",
			"location": {
				"x": 0,
				"y": 3,
				"r": "Horizontal"
			}
		},
		{
			"_id": "BP_Backpack686421_821301",
			"_tpl": "5734779624597737e04bf329",
			"parentId": "Backpack686421",
			"slotId": "main",
			"location": {
				"x": 0,
				"y": 4,
				"r": "Horizontal"
			}
		},
		{
			"_id": "ArmorVest433776",
			"_tpl": "5b44d22286f774172b0c9de8",
			"parentId": "5c6687d65e9d882c8841f0fd",
			"slotId": "ArmorVest",
			"upd": {
				"Repairable": {
					"MaxDurability": 70,
					"Durability": 12
				}
			}
		},
		{
			"_id": "Pocket_709948",
			"_tpl": "5780cf7f2459777de4559322",
			"parentId": "5c6687d65e9d882c8841f121",
			"slotId": "pocket1",
			"location": {
				"x": 0,
				"y": 0,
				"r": "Horizontal"
			},
			"upd": {
				"SpawnedInSession": true
			}
		},
		{
			"_id": "Pocket_194691",
			"_tpl": "5d80c66d86f774405611c7d6",
			"parentId": "5c6687d65e9d882c8841f121",
			"slotId": "pocket2",
			"location": {
				"x": 0,
				"y": 0,
				"r": "Horizontal"
			},
			"upd": {
				"SpawnedInSession": true
			}
		}
	],
	"equipment": "5c6687d65e9d882c8841f0fd",
	"stash": "5c6687d65e9d882c8841f0fc",
	"questRaidItems": "5c6687d65e9d882c8841f0fe",
	"questStashItems": "5c6687d65e9d882c8841f0ff",
	"fastPanel": {}
}