{
	"items": [
		{
			"_id": "5c6687d65e9d882c8841f0fd",
			"_tpl": "55d7217a4bdc2d86028b456d"
		},
		{
			"_id": "5c6687d65e9d882c8841f121",
			"_tpl": "557ffd194bdc2d28148b457f",
			"parentId": "5c6687d65e9d882c8841f0fd",
			"slotId": "Pockets"
		},
		{
			"_id": "5c6687d65e9d882c8841f0fc",
			"_tpl": "566abbc34bdc2d92178b4576"
		},
		{
			"_id": "5c6687d65e9d882c8841f0ff",
			"_tpl": "5963866b86f7747bfa1c4462"
		},
		{
			"_id": "5c6687d65e9d882c8841f0fe",
			"_tpl": "5963866286f7747bf429b572"
		},
		{
			"_id": "TacticalVest628784",
			"_tpl": "544a5caa4bdc2d1a388b4568",
			"parentId": "5c6687d65e9d882c8841f0fd",
			"slotId": "TacticalVest"
		},
		{
			"_id": "I210101559414001744fJLzB",
			"_tpl": "5e00903ae9dc277128008b87",
			"parentId": "5c6687d65e9d882c8841f0fd",
			"slotId": "FirstPrimaryWeapon"
		},
		{
			"_id": "MagazineWeaponScav8950",
			"_tpl": "5de8eac42a78646d96665d91",
			"parentId": "I210101559414001744fJLzB",
			"slotId": "mod_magazine"
		},
		{
			"_id": "AmmoMag19202",
			"_tpl": "5c0d56a986f774449d5de529",
			"parentId": "MagazineWeaponScav8950",
			"slotId": "cartridges",
			"upd": {
				"StackObjectsCount": 30
			}
		},
		{
			"_id": "I210101553403007833IPitO",
			"_tpl": "5de8f237bbaf010b10528a70",
			"parentId": "I210101559414001744fJLzB",
			"slotId": "mod_muzzle"
		},
		{
			"_id": "I210101552045761767lZJY9",
			"_tpl": "5e0090f7e9dc277128008b93",
			"parentId": "I210101559414001744fJLzB",
			"slotId": "mod_reciever"
		},
		{
			"_id": "I210101556121394926e9TW2",
			"_tpl": "5de922d4b11454561e39239f",
			"parentId": "I210101559414001744fJLzB",
			"slotId": "mod_charge"
		},
		{
			"_id": "I210101558824284123FRQx6",
			"_tpl": "5de8f2d5b74cd90030650c72",
			"parentId": "I210101553403007833IPitO",
			"slotId": "mod_muzzle"
		},
		{
			"_id": "I2101015597403640488wa8n",
			"_tpl": "5cc9c20cd7f00c001336c65d",
			"parentId": "I210101553403007833IPitO",
			"slotId": "mod_tactical",
			"upd": {
				"Light": {
					"IsActive": true,
					"SelectedMode": 0
				}
			}
		},
		{
			"_id": "I210101552895798667tB8uu",
			"_tpl": "5a33b2c9c4a282000c5a9511",
			"parentId": "I210101552045761767lZJY9",
			"slotId": "mod_scope"
		},
		{
			"_id": "I210101553324612894w76PR",
			"_tpl": "5a32aa8bc4a2826c6e06d737",
			"parentId": "I210101552895798667tB8uu",
			"slotId": "mod_scope",
			"upd": {
				"Sight": {
					"SelectedSightMode": 0
				}
			}
		},
		{
			"_id": "mag0Vest160263",
			"_tpl": "5de8eaadbbaf010b10528a6d",
			"parentId": "TacticalVest628784",
			"slotId": "1",
			"location": {
				"x": 0,
				"y": 0,
				"r": "Horizontal"
			}
		},
		{
			"_id": "AmmoMag0Vest457696",
			"_tpl": "5c0d56a986f774449d5de529",
			"parentId": "mag0Vest160263",
			"slotId": "cartridges",
			"upd": {
				"StackObjectsCount": 25
			}
		},
		{
			"_id": "mag2Vest729240",
			"_tpl": "5de8eaadbbaf010b10528a6d",
			"parentId": "TacticalVest628784",
			"slotId": "4",
			"location": {
				"x": 0,
				"y": 0,
				"r": "Horizontal"
			}
		},
		{
			"_id": "AmmoMag2Vest495168",
			"_tpl": "56d59d3ad2720bdb418b4577",
			"parentId": "mag2Vest729240",
			"slotId": "cartridges",
			"upd": {
				"StackObjectsCount": 25
			}
		},
		{
			"_id": "mag0Vest378482",
			"_tpl": "5de8eaadbbaf010b10528a6d",
			"parentId": "TacticalVest628784",
			"slotId": "5",
			"location": {
				"x": 0,
				"y": 0,
				"r": "Horizontal"
			}
		},
		{
			"_id": "AmmoMag0Vest440511",
			"_tpl": "5c0d56a986f774449d5de529",
			"parentId": "mag0Vest378482",
			"slotId": "cartridges",
			"upd": {
				"StackObjectsCount": 25
			}
		},
		{
			"_id": "mag0Vest977962",
			"_tpl": "5de8eaadbbaf010b10528a6d",
			"parentId": "TacticalVest628784",
			"slotId": "5",
			"location": {
				"x": 1,
				"y": 0,
				"r": "Horizontal"
			}
		},
		{
			"_id": "AmmoMag0Vest83742",
			"_tpl": "5c0d56a986f774449d5de529",
			"parentId": "mag0Vest977962",
			"slotId": "cartridges",
			"upd": {
				"StackObjectsCount": 25
			}
		},
		{
			"_id": "StackAmmo64210033246",
			"_tpl": "58864a4f2459770fcc257101",
			"parentId": "TacticalVest628784",
			"slotId": "8",
			"upd": {
				"StackObjectsCount": 16
			}
		},
		{
			"_id": "StackAmmo90889338496",
			"_tpl": "5c3df7d588a4501f290594e5",
			"parentId": "TacticalVest628784",
			"slotId": "12",
			"upd": {
				"StackObjectsCount": 27
			}
		},
		{
			"_id": "Scabbard948318",
			"_tpl": "5c0116620db834001808a647",
			"parentId": "5c6687d65e9d882c8841f0fd",
			"slotId": "Scabbard"
		},
		{
			"_id": "Pocket_769578",
			"_tpl": "590a3b0486f7743954552bdb",
			"parentId": "5c6687d65e9d882c8841f121",
			"slotId": "pocket1",
			"location": {
				"x": 0,
				"y": 0,
				"r": "Horizontal"
			},
			"upd": {
				"SpawnedInSession": true
			}
		},
		{
			"_id": "Pocket_533576",
			"_tpl": "590a3b0486f7743954552bdb",
			"parentId": "5c6687d65e9d882c8841f121",
			"slotId": "pocket2",
			"location": {
				"x": 0,
				"y": 0,
				"r": "Horizontal"
			},
			"upd": {
				"SpawnedInSession": true
			}
		},
		{
			"_id": "Pocket_635628",
			"_tpl": "573474f924597738002c6174",
			"parentId": "5c6687d65e9d882c8841f121",
			"slotId": "pocket3",
			"location": {
				"x": 0,
				"y": 0,
				"r": "Horizontal"
			},
			"upd": {
				"SpawnedInSession": true
			}
		}
	],
	"equipment": "5c6687d65e9d882c8841f0fd",
	"stash": "5c6687d65e9d882c8841f0fc",
	"questRaidItems": "5c6687d65e9d882c8841f0fe",
	"questStashItems": "5c6687d65e9d882c8841f0ff",
	"fastPanel": {}
}