{
	"Id": "Lootable_00194",
	"IsStatic": true,
	"useGravity": true,
	"randomRotation": false,
	"Position": {
		"x": 0,
		"y": 0,
		"z": 0
	},
	"Rotation": {
		"x": 0,
		"y": 0,
		"z": 0
	},
	"IsGroupPosition": false,
	"GroupPositions": [],
	"Root": "5db5d18a8bcb9e33ce402397",
	"Items": [
		{
			"_id": "5db5d18a8bcb9e33ce402397",
			"_tpl": "578f87a3245977356274f2cb"
		},
		{
			"_id": "5db5d18a8bcb9e33ce402398",
			"_tpl": "59e3556c86f7741776641ac2",
			"parentId": "5db5d18a8bcb9e33ce402397",
			"slotId": "main",
			"location": {
				"x": 0,
				"y": 0,
				"r": 0
			}
		},
		{
			"_id": "5db5d18a8bcb9e33ce402399",
			"_tpl": "59e358a886f7741776641ac3",
			"parentId": "5db5d18a8bcb9e33ce402397",
			"slotId": "main",
			"location": {
				"x": 1,
				"y": 0,
				"r": 0
			}
		},
		{
			"_id": "5db5d18a8bcb9e33ce40239a",
			"_tpl": "573477e124597737dd42e191",
			"parentId": "5db5d18a8bcb9e33ce402397",
			"slotId": "main",
			"location": {
				"x": 2,
				"y": 0,
				"r": 0
			}
		}
	]
}