{
	"Id": "Lootable_00372",
	"IsStatic": true,
	"useGravity": true,
	"randomRotation": false,
	"Position": {
		"x": 0,
		"y": 0,
		"z": 0
	},
	"Rotation": {
		"x": 0,
		"y": 0,
		"z": 0
	},
	"IsGroupPosition": false,
	"GroupPositions": [],
	"Root": "5ea2d1eb86f774200a135e36",
	"Items": [
		{
			"_id": "5ea2d1eb86f774200a135e36",
			"_tpl": "5d6d2bb386f774785b07a77a"
		},
		{
			"_id": "5ea2d1eb86f774200a135e37",
			"_tpl": "5c13cd2486f774072c757944",
			"parentId": "5ea2d1eb86f774200a135e36",
			"slotId": "main",
			"location": {
				"x": 0,
				"y": 0,
				"r": 0
			}
		},
		{
			"_id": "5ea2d1eb86f774200a135e38",
			"_tpl": "5737207f24597760ff7b25f2",
			"parentId": "5ea2d1eb86f774200a135e36",
			"slotId": "main",
			"location": {
				"x": 1,
				"y": 0,
				"r": 0
			},
			"upd": {
				"StackObjectsCount": 5
			}
		},
		{
			"_id": "5ea2d1eb86f774200a135e39",
			"_tpl": "5672cb304bdc2dc2088b456a",
			"parentId": "5ea2d1eb86f774200a135e36",
			"slotId": "main",
			"location": {
				"x": 2,
				"y": 0,
				"r": 0
			}
		}
	]
}