{
	"Id": "Lootable_00372",
	"IsStatic": true,
	"useGravity": true,
	"randomRotation": false,
	"Position": {
		"x": 0,
		"y": 0,
		"z": 0
	},
	"Rotation": {
		"x": 0,
		"y": 0,
		"z": 0
	},
	"IsGroupPosition": false,
	"GroupPositions": [],
	"Root": "5ea2d20f86f774029868b21f",
	"Items": [
		{
			"_id": "5ea2d20f86f774029868b21f",
			"_tpl": "5d6d2bb386f774785b07a77a"
		},
		{
			"_id": "5ea2d20f86f774029868b220",
			"_tpl": "5d40425986f7743185265461",
			"parentId": "5ea2d20f86f774029868b21f",
			"slotId": "main",
			"location": {
				"x": 0,
				"y": 0,
				"r": 0
			}
		},
		{
			"_id": "5ea2d20f86f774029868b221",
			"_tpl": "577e1c9d2459773cd707c525",
			"parentId": "5ea2d20f86f774029868b21f",
			"slotId": "main",
			"location": {
				"x": 1,
				"y": 0,
				"r": 0
			}
		},
		{
			"_id": "5ea2d20f86f774029868b222",
			"_tpl": "5bd70322209c4d00d7167b8f",
			"parentId": "5ea2d20f86f774029868b21f",
			"slotId": "main",
			"location": {
				"x": 0,
				"y": 1,
				"r": 0
			}
		},
		{
			"_id": "5ea2d20f86f774029868b223",
			"_tpl": "5ba264f6d4351e0034777d52",
			"parentId": "5ea2d20f86f774029868b222",
			"slotId": "mod_magazine"
		},
		{
			"_id": "5ea2d20f86f774029868b228",
			"_tpl": "5ba2678ad4351e44f824b344",
			"parentId": "5ea2d20f86f774029868b223",
			"slotId": "cartridges",
			"upd": {
				"StackObjectsCount": 9
			}
		},
		{
			"_id": "5ea2d20f86f774029868b224",
			"_tpl": "5ba26acdd4351e003562908e",
			"parentId": "5ea2d20f86f774029868b222",
			"slotId": "mod_muzzle"
		},
		{
			"_id": "5ea2d20f86f774029868b225",
			"_tpl": "5ba26b01d4351e0085325a51",
			"parentId": "5ea2d20f86f774029868b222",
			"slotId": "mod_sight_front"
		},
		{
			"_id": "5ea2d20f86f774029868b226",
			"_tpl": "5ba26b17d4351e00367f9bdd",
			"parentId": "5ea2d20f86f774029868b222",
			"slotId": "mod_sight_rear"
		},
		{
			"_id": "5ea2d20f86f774029868b227",
			"_tpl": "5bd704e7209c4d00d7167c31",
			"parentId": "5ea2d20f86f774029868b222",
			"slotId": "mod_stock"
		},
		{
			"_id": "5ea2d20f86f774029868b229",
			"_tpl": "56dff216d2720bbd668b4568",
			"parentId": "5ea2d20f86f774029868b21f",
			"slotId": "main",
			"location": {
				"x": 0,
				"y": 2,
				"r": 0
			},
			"upd": {
				"StackObjectsCount": 57
			}
		}
	]
}