{
	"Id": "Lootable_00018",
	"IsStatic": true,
	"useGravity": true,
	"randomRotation": false,
	"Position": {
		"x": 0,
		"y": 0,
		"z": 0
	},
	"Rotation": {
		"x": 0,
		"y": 0,
		"z": 0
	},
	"IsGroupPosition": false,
	"GroupPositions": [],
	"Root": "5ea2d20386f77474bf0145ba",
	"Items": [
		{
			"_id": "5ea2d20386f77474bf0145ba",
			"_tpl": "578f87ad245977356274f2cc"
		},
		{
			"_id": "5ea2d20386f77474bf0145bb",
			"_tpl": "5755356824597772cb798962",
			"parentId": "5ea2d20386f77474bf0145ba",
			"slotId": "main",
			"location": {
				"x": 0,
				"y": 0,
				"r": 0
			}
		},
		{
			"_id": "5ea2d20386f77474bf0145bc",
			"_tpl": "57d17c5e2459775a5c57d17d",
			"parentId": "5ea2d20386f77474bf0145ba",
			"slotId": "main",
			"location": {
				"x": 1,
				"y": 0,
				"r": 0
			}
		},
		{
			"_id": "5ea2d20386f77474bf0145bd",
			"_tpl": "57ade1442459771557167e15",
			"parentId": "5ea2d20386f77474bf0145ba",
			"slotId": "main",
			"location": {
				"x": 2,
				"y": 0,
				"r": 0
			}
		},
		{
			"_id": "5ea2d20386f77474bf0145be",
			"_tpl": "590c678286f77426c9660122",
			"parentId": "5ea2d20386f77474bf0145ba",
			"slotId": "main",
			"location": {
				"x": 4,
				"y": 0,
				"r": 0
			}
		}
	]
}