{
	"Id": "Lootable_00009",
	"IsStatic": true,
	"useGravity": true,
	"randomRotation": false,
	"Position": {
		"x": 0,
		"y": 0,
		"z": 0
	},
	"Rotation": {
		"x": 0,
		"y": 0,
		"z": 0
	},
	"IsGroupPosition": false,
	"GroupPositions": [],
	"Root": "5dd2955f86f774793e1ed98e",
	"Items": [
		{
			"_id": "5dd2955f86f774793e1ed98e",
			"_tpl": "5909d45286f77465a8136dc6"
		},
		{
			"_id": "5dd2955f86f774793e1ed98f",
			"_tpl": "56dff0bed2720bb0668b4567",
			"parentId": "5dd2955f86f774793e1ed98e",
			"slotId": "main",
			"location": {
				"x": 0,
				"y": 0,
				"r": 0
			},
			"upd": {
				"StackObjectsCount": 7
			}
		},
		{
			"_id": "5dd2955f86f774793e1ed990",
			"_tpl": "560d61e84bdc2da74d8b4571",
			"parentId": "5dd2955f86f774793e1ed98e",
			"slotId": "main",
			"location": {
				"x": 1,
				"y": 0,
				"r": 0
			},
			"upd": {
				"StackObjectsCount": 8
			}
		},
		{
			"_id": "5dd2955f86f774793e1ed991",
			"_tpl": "59e6542b86f77411dc52a77a",
			"parentId": "5dd2955f86f774793e1ed98e",
			"slotId": "main",
			"location": {
				"x": 2,
				"y": 0,
				"r": 0
			},
			"upd": {
				"StackObjectsCount": 12
			}
		},
		{
			"_id": "5dd2955f86f774793e1ed992",
			"_tpl": "56dff3afd2720bba668b4567",
			"parentId": "5dd2955f86f774793e1ed98e",
			"slotId": "main",
			"location": {
				"x": 0,
				"y": 1,
				"r": 0
			},
			"upd": {
				"StackObjectsCount": 7
			}
		}
	]
}