{
	"Id": "Lootable_00431",
	"IsStatic": true,
	"useGravity": true,
	"randomRotation": false,
	"Position": {
		"x": 0,
		"y": 0,
		"z": 0
	},
	"Rotation": {
		"x": 0,
		"y": 0,
		"z": 0
	},
	"IsGroupPosition": false,
	"GroupPositions": [],
	"Root": "5db5d083cd1e3d3a94509d7d",
	"Items": [
		{
			"_id": "5db5d083cd1e3d3a94509d7d",
			"_tpl": "5909d5ef86f77467974efbd8"
		},
		{
			"_id": "5db5d083cd1e3d3a94509d7e",
			"_tpl": "591af10186f774139d495f0e",
			"parentId": "5db5d083cd1e3d3a94509d7d",
			"slotId": "main",
			"location": {
				"x": 0,
				"y": 0,
				"r": 0
			}
		},
		{
			"_id": "5db5d083cd1e3d3a94509d7f",
			"_tpl": "57acb6222459771ec34b5cb0",
			"parentId": "5db5d083cd1e3d3a94509d7d",
			"slotId": "main",
			"location": {
				"x": 2,
				"y": 0,
				"r": 0
			}
		}
	]
}