{
	"Id": "Lootable_00100",
	"IsStatic": true,
	"useGravity": true,
	"randomRotation": false,
	"Position": {
		"x": 0,
		"y": 0,
		"z": 0
	},
	"Rotation": {
		"x": 0,
		"y": 0,
		"z": 0
	},
	"IsGroupPosition": false,
	"GroupPositions": [],
	"Root": "5ea2d1ce86f77460da76d09b",
	"Items": [
		{
			"_id": "5ea2d1ce86f77460da76d09b",
			"_tpl": "5909d45286f77465a8136dc6"
		},
		{
			"_id": "5ea2d1ce86f77460da76d09c",
			"_tpl": "59e6906286f7746c9f75e847",
			"parentId": "5ea2d1ce86f77460da76d09b",
			"slotId": "main",
			"location": {
				"x": 0,
				"y": 0,
				"r": 0
			},
			"upd": {
				"StackObjectsCount": 57
			}
		},
		{
			"_id": "5ea2d1ce86f77460da76d09d",
			"_tpl": "560d5e524bdc2d25448b4571",
			"parentId": "5ea2d1ce86f77460da76d09b",
			"slotId": "main",
			"location": {
				"x": 1,
				"y": 0,
				"r": 0
			},
			"upd": {
				"StackObjectsCount": 6
			}
		},
		{
			"_id": "5ea2d1ce86f77460da76d09e",
			"_tpl": "560d5e524bdc2d25448b4571",
			"parentId": "5ea2d1ce86f77460da76d09b",
			"slotId": "main",
			"location": {
				"x": 2,
				"y": 0,
				"r": 0
			},
			"upd": {
				"StackObjectsCount": 9
			}
		}
	]
}