{
	"items": [
		{
			"_id": "5c6687d65e9d882c8841f0fd",
			"_tpl": "55d7217a4bdc2d86028b456d"
		},
		{
			"_id": "5c6687d65e9d882c8841f121",
			"_tpl": "557ffd194bdc2d28148b457f",
			"parentId": "5c6687d65e9d882c8841f0fd",
			"slotId": "Pockets"
		},
		{
			"_id": "5c6687d65e9d882c8841f0fc",
			"_tpl": "566abbc34bdc2d92178b4576"
		},
		{
			"_id": "5c6687d65e9d882c8841f0ff",
			"_tpl": "5963866b86f7747bfa1c4462"
		},
		{
			"_id": "5c6687d65e9d882c8841f0fe",
			"_tpl": "5963866286f7747bf429b572"
		},
		{
			"_id": "TacticalVest532087",
			"_tpl": "5ca20abf86f77418567a43f2",
			"parentId": "5c6687d65e9d882c8841f0fd",
			"slotId": "TacticalVest"
		},
		{
			"_id": "I081928339278444757BTN7D",
			"_tpl": "5d43021ca4b9362eab4b5e25",
			"parentId": "5c6687d65e9d882c8841f0fd",
			"slotId": "FirstPrimaryWeapon"
		},
		{
			"_id": "I081928337001172833So0Zp",
			"_tpl": "57af48872459771f0b2ebf11",
			"parentId": "I081928339278444757BTN7D",
			"slotId": "mod_pistol_grip",
			"upd": {
				"SpawnedInSession": true
			}
		},
		{
			"_id": "MagazineWeaponScav9051",
			"_tpl": "5d1340cad7ad1a0b0b249869",
			"parentId": "I081928339278444757BTN7D",
			"slotId": "mod_magazine"
		},
		{
			"_id": "AmmoMag12573",
			"_tpl": "54527ac44bdc2d36668b4567",
			"parentId": "MagazineWeaponScav9051",
			"slotId": "cartridges",
			"upd": {
				"StackObjectsCount": 30
			}
		},
		{
			"_id": "I081928338417034149juzps",
			"_tpl": "5d4405aaa4b9361e6a4e6bd3",
			"parentId": "I081928339278444757BTN7D",
			"slotId": "mod_reciever",
			"upd": {
				"SpawnedInSession": true
			}
		},
		{
			"_id": "I081928338899030425ZGpYd",
			"_tpl": "5947eab886f77475961d96c5",
			"parentId": "I081928339278444757BTN7D",
			"slotId": "mod_stock",
			"upd": {
				"SpawnedInSession": true
			}
		},
		{
			"_id": "I0819283388082813932SzND",
			"_tpl": "5d44334ba4b9362b346d1948",
			"parentId": "I081928339278444757BTN7D",
			"slotId": "mod_charge",
			"upd": {
				"SpawnedInSession": true
			}
		},
		{
			"_id": "I081928332872988754RLbgI",
			"_tpl": "59f9d81586f7744c7506ee62",
			"parentId": "I081928338417034149juzps",
			"slotId": "mod_scope",
			"upd": {
				"SpawnedInSession": true
			}
		},
		{
			"_id": "I081928334746789358CHBCk",
			"_tpl": "55d3632e4bdc2d972f8b4569",
			"parentId": "I081928338417034149juzps",
			"slotId": "mod_barrel",
			"upd": {
				"SpawnedInSession": true
			}
		},
		{
			"_id": "I081928334613064265asM8G",
			"_tpl": "5c78f2792e221600106f4683",
			"parentId": "I081928338417034149juzps",
			"slotId": "mod_handguard",
			"upd": {
				"SpawnedInSession": true
			}
		},
		{
			"_id": "I081928334091944031QFj4D",
			"_tpl": "5cf6937cd7f00c056c53fb39",
			"parentId": "I081928334746789358CHBCk",
			"slotId": "mod_muzzle",
			"upd": {
				"SpawnedInSession": true
			}
		},
		{
			"_id": "I081928334495873768Atn4W",
			"_tpl": "5d00ec68d7ad1a04a067e5be",
			"parentId": "I081928334746789358CHBCk",
			"slotId": "mod_gas_block",
			"upd": {
				"SpawnedInSession": true
			}
		},
		{
			"_id": "I081928332312036408fbppg",
			"_tpl": "57cffcd624597763133760c5",
			"parentId": "I081928334613064265asM8G",
			"slotId": "mod_foregrip",
			"upd": {
				"SpawnedInSession": true
			}
		},
		{
			"_id": "mag0Vest20325",
			"_tpl": "5c6d42cb2e2216000e69d7d1",
			"parentId": "TacticalVest532087",
			"slotId": "1",
			"location": {
				"x": 0,
				"y": 0,
				"r": "Horizontal"
			}
		},
		{
			"_id": "AmmoMag0Vest871348",
			"_tpl": "54527a984bdc2d4e668b4567",
			"parentId": "mag0Vest20325",
			"slotId": "cartridges",
			"upd": {
				"StackObjectsCount": 30
			}
		},
		{
			"_id": "mag1Vest2307",
			"_tpl": "5c6d42cb2e2216000e69d7d1",
			"parentId": "TacticalVest532087",
			"slotId": "3",
			"location": {
				"x": 0,
				"y": 0,
				"r": "Horizontal"
			}
		},
		{
			"_id": "AmmoMag1Vest994653",
			"_tpl": "59e6927d86f77411da468256",
			"parentId": "mag1Vest2307",
			"slotId": "cartridges",
			"upd": {
				"StackObjectsCount": 30
			}
		},
		{
			"_id": "Scabbard356917",
			"_tpl": "57e26ea924597715ca604a09",
			"parentId": "5c6687d65e9d882c8841f0fd",
			"slotId": "Scabbard"
		},
		{
			"_id": "Headwear188845",
			"_tpl": "5c08f87c0db8340019124324",
			"parentId": "5c6687d65e9d882c8841f0fd",
			"slotId": "Headwear"
		},
		{
			"_id": "ArmorVest389698",
			"_tpl": "59e7635f86f7742cbf2c1095",
			"parentId": "5c6687d65e9d882c8841f0fd",
			"slotId": "ArmorVest",
			"upd": {
				"Repairable": {
					"MaxDurability": 40,
					"Durability": 8
				}
			}
		}
	],
	"equipment": "5c6687d65e9d882c8841f0fd",
	"stash": "5c6687d65e9d882c8841f0fc",
	"questRaidItems": "5c6687d65e9d882c8841f0fe",
	"questStashItems": "5c6687d65e9d882c8841f0ff",
	"fastPanel": {}
}