{
	"Id": "Lootable_00166",
	"IsStatic": true,
	"useGravity": true,
	"randomRotation": false,
	"Position": {
		"x": 0,
		"y": 0,
		"z": 0
	},
	"Rotation": {
		"x": 0,
		"y": 0,
		"z": 0
	},
	"IsGroupPosition": false,
	"GroupPositions": [],
	"Root": "5d31e40a645bb70f94277f47",
	"Items": [
		{
			"_id": "5d31e40a645bb70f94277f47",
			"_tpl": "578f87ad245977356274f2cc"
		},
		{
			"_id": "5d31e40a645bb70f94277f48",
			"_tpl": "56def37dd2720bec348b456a",
			"parentId": "5d31e40a645bb70f94277f47",
			"slotId": "main",
			"location": {
				"x": 0,
				"y": 0,
				"r": 0
			}
		},
		{
			"_id": "5d31e40a645bb70f94277f49",
			"_tpl": "56dff3afd2720bba668b4567",
			"parentId": "5d31e40a645bb70f94277f47",
			"slotId": "main",
			"location": {
				"x": 1,
				"y": 0,
				"r": 0
			},
			"upd": {
				"StackObjectsCount": 4
			}
		},
		{
			"_id": "5d31e40a645bb70f94277f4a",
			"_tpl": "564ca99c4bdc2d16268b4589",
			"parentId": "5d31e40a645bb70f94277f47",
			"slotId": "main",
			"location": {
				"x": 2,
				"y": 0,
				"r": 0
			}
		}
	]
}