{
	"items": [
		{
			"_id": "5c6687d65e9d882c8841f0fd",
			"_tpl": "55d7217a4bdc2d86028b456d"
		},
		{
			"_id": "5c6687d65e9d882c8841f121",
			"_tpl": "557ffd194bdc2d28148b457f",
			"parentId": "5c6687d65e9d882c8841f0fd",
			"slotId": "Pockets"
		},
		{
			"_id": "5c6687d65e9d882c8841f0fc",
			"_tpl": "566abbc34bdc2d92178b4576"
		},
		{
			"_id": "5c6687d65e9d882c8841f0ff",
			"_tpl": "5963866b86f7747bfa1c4462"
		},
		{
			"_id": "5c6687d65e9d882c8841f0fe",
			"_tpl": "5963866286f7747bf429b572"
		},
		{
			"_id": "TacticalVest796366",
			"_tpl": "5c0e9f2c86f77432297fe0a3",
			"parentId": "5c6687d65e9d882c8841f0fd",
			"slotId": "TacticalVest"
		},
		{
			"_id": "I07217137389166759Xyr4s9",
			"_tpl": "5644bd2b4bdc2d3b4c8b4572",
			"parentId": "5c6687d65e9d882c8841f0fd",
			"slotId": "FirstPrimaryWeapon"
		},
		{
			"_id": "I07217134561597806KpWKH9",
			"_tpl": "5649ab884bdc2ded0b8b457f",
			"parentId": "I07217137389166759Xyr4s9",
			"slotId": "mod_muzzle",
			"upd": {
				"SpawnedInSession": true
			}
		},
		{
			"_id": "I07217139151119495h14ZC1",
			"_tpl": "5beec8ea0db834001a6f9dbf",
			"parentId": "I07217137389166759Xyr4s9",
			"slotId": "mod_pistol_grip",
			"upd": {
				"SpawnedInSession": true
			}
		},
		{
			"_id": "I07217136917392430ufyTiJ",
			"_tpl": "5d2c770c48f0354b4a07c100",
			"parentId": "I07217137389166759Xyr4s9",
			"slotId": "mod_reciever",
			"upd": {
				"SpawnedInSession": true
			}
		},
		{
			"_id": "I07217134417347628oz3V9o",
			"_tpl": "5649b0544bdc2d1b2b8b458a",
			"parentId": "I07217137389166759Xyr4s9",
			"slotId": "mod_sight_rear",
			"upd": {
				"SpawnedInSession": true
			}
		},
		{
			"_id": "I07217137043539394rnvhn1",
			"_tpl": "5649b0fc4bdc2d17108b4588",
			"parentId": "I07217137389166759Xyr4s9",
			"slotId": "mod_stock",
			"upd": {
				"SpawnedInSession": true
			}
		},
		{
			"_id": "MagazineWeaponScav1802",
			"_tpl": "55d480c04bdc2d1d4e8b456a",
			"parentId": "I07217137389166759Xyr4s9",
			"slotId": "mod_magazine"
		},
		{
			"_id": "AmmoMag11512",
			"_tpl": "56dff421d2720b5f5a8b4567",
			"parentId": "MagazineWeaponScav1802",
			"slotId": "cartridges",
			"upd": {
				"StackObjectsCount": 30
			}
		},
		{
			"_id": "I07217132120771126hrviO4",
			"_tpl": "59e0bdb186f774156f04ce82",
			"parentId": "I07217139408701330fCec5S",
			"slotId": "mod_mount_000",
			"upd": {
				"SpawnedInSession": true
			}
		},
		{
			"_id": "I07217135239785335Cgkr96",
			"_tpl": "5a9d6d13a2750c00164f6b03",
			"parentId": "I07217139408701330fCec5S",
			"slotId": "mod_foregrip",
			"upd": {
				"SpawnedInSession": true
			}
		},
		{
			"_id": "I072171329341872945ureng",
			"_tpl": "5d2369418abbc306c62e0c80",
			"parentId": "I07217132120771126hrviO4",
			"slotId": "mod_tactical",
			"upd": {
				"SpawnedInSession": true
			}
		},
		{
			"_id": "I07217134875416847ix9hLt",
			"_tpl": "59f8a37386f7747af3328f06",
			"parentId": "I07217135239785335Cgkr96",
			"slotId": "mod_foregrip",
			"upd": {
				"SpawnedInSession": true
			}
		},
		{
			"_id": "I07217135491250577JNXirw",
			"_tpl": "5d2dc3e548f035404a1a4798",
			"parentId": "I07217136917392430ufyTiJ",
			"slotId": "mod_scope",
			"upd": {
				"SpawnedInSession": true
			}
		},
		{
			"_id": "I07217137607868430gKz6ve",
			"_tpl": "5a0c59791526d8dba737bba7",
			"parentId": "I07217137043539394rnvhn1",
			"slotId": "mod_stock",
			"upd": {
				"SpawnedInSession": true
			}
		},
		{
			"_id": "mag0Vest990393",
			"_tpl": "55d480c04bdc2d1d4e8b456a",
			"parentId": "TacticalVest796366",
			"slotId": "1",
			"location": {
				"x": 0,
				"y": 0,
				"r": "Horizontal"
			}
		},
		{
			"_id": "AmmoMag0Vest777996",
			"_tpl": "56dff2ced2720bb4668b4567",
			"parentId": "mag0Vest990393",
			"slotId": "cartridges",
			"upd": {
				"StackObjectsCount": 30
			}
		},
		{
			"_id": "mag2Vest871337",
			"_tpl": "55d480c04bdc2d1d4e8b456a",
			"parentId": "TacticalVest796366",
			"slotId": "4",
			"location": {
				"x": 0,
				"y": 0,
				"r": "Horizontal"
			}
		},
		{
			"_id": "AmmoMag2Vest631662",
			"_tpl": "56dff421d2720b5f5a8b4567",
			"parentId": "mag2Vest871337",
			"slotId": "cartridges",
			"upd": {
				"StackObjectsCount": 30
			}
		},
		{
			"_id": "mag3Vest119673",
			"_tpl": "55d480c04bdc2d1d4e8b456a",
			"parentId": "TacticalVest796366",
			"slotId": "6",
			"location": {
				"x": 0,
				"y": 0,
				"r": "Horizontal"
			}
		},
		{
			"_id": "AmmoMag3Vest25686",
			"_tpl": "56dff421d2720b5f5a8b4567",
			"parentId": "mag3Vest119673",
			"slotId": "cartridges",
			"upd": {
				"StackObjectsCount": 30
			}
		},
		{
			"_id": "Scabbard9408",
			"_tpl": "5c0116620db834001808a647",
			"parentId": "5c6687d65e9d882c8841f0fd",
			"slotId": "Scabbard"
		},
		{
			"_id": "Headwear801464",
			"_tpl": "5aa2b8d7e5b5b00014028f4a",
			"parentId": "5c6687d65e9d882c8841f0fd",
			"slotId": "Headwear"
		},
		{
			"_id": "FaceCover896153",
			"_tpl": "572b7f1624597762ae139822",
			"parentId": "5c6687d65e9d882c8841f0fd",
			"slotId": "FaceCover"
		},
		{
			"_id": "Backpack255219",
			"_tpl": "5ca20d5986f774331e7c9602",
			"parentId": "5c6687d65e9d882c8841f0fd",
			"slotId": "Backpack"
		},
		{
			"_id": "BP_Backpack255219_627468",
			"_tpl": "575146b724597720a27126d5",
			"parentId": "Backpack255219",
			"slotId": "main",
			"location": {
				"x": 0,
				"y": 0,
				"r": "Horizontal"
			}
		},
		{
			"_id": "BP_Backpack255219_652247",
			"_tpl": "5c471c442e221602b542a6f8",
			"parentId": "Backpack255219",
			"slotId": "main",
			"location": {
				"x": 0,
				"y": 2,
				"r": "Horizontal"
			}
		}
	],
	"equipment": "5c6687d65e9d882c8841f0fd",
	"stash": "5c6687d65e9d882c8841f0fc",
	"questRaidItems": "5c6687d65e9d882c8841f0fe",
	"questStashItems": "5c6687d65e9d882c8841f0ff",
	"fastPanel": {}
}