{
	"Id": "Lootable_00022",
	"IsStatic": true,
	"useGravity": true,
	"randomRotation": false,
	"Position": {
		"x": 0,
		"y": 0,
		"z": 0
	},
	"Rotation": {
		"x": 0,
		"y": 0,
		"z": 0
	},
	"IsGroupPosition": false,
	"GroupPositions": [],
	"Root": "5e06751f5fd55152ed5e2bbf",
	"Items": [
		{
			"_id": "5e06751f5fd55152ed5e2bbf",
			"_tpl": "578f87ad245977356274f2cc"
		},
		{
			"_id": "5e0675205fd55152ed5e2bc0",
			"_tpl": "584984812459776a704a82a6",
			"parentId": "5e06751f5fd55152ed5e2bbf",
			"slotId": "main",
			"location": {
				"x": 0,
				"y": 0,
				"r": 0
			}
		},
		{
			"_id": "5e0675205fd55152ed5e2bc1",
			"_tpl": "5448ff904bdc2d6f028b456e",
			"parentId": "5e06751f5fd55152ed5e2bbf",
			"slotId": "main",
			"location": {
				"x": 1,
				"y": 0,
				"r": 0
			}
		},
		{
			"_id": "5e0675205fd55152ed5e2bc2",
			"_tpl": "5751a25924597722c463c472",
			"parentId": "5e06751f5fd55152ed5e2bbf",
			"slotId": "main",
			"location": {
				"x": 2,
				"y": 0,
				"r": 0
			}
		},
		{
			"_id": "5e0675205fd55152ed5e2bc3",
			"_tpl": "57ffaea724597779f52b3a4d",
			"parentId": "5e06751f5fd55152ed5e2bbf",
			"slotId": "main",
			"location": {
				"x": 3,
				"y": 0,
				"r": 0
			}
		}
	]
}