{
	"Id": "Lootable_00228",
	"IsStatic": true,
	"useGravity": true,
	"randomRotation": false,
	"Position": {
		"x": 0,
		"y": 0,
		"z": 0
	},
	"Rotation": {
		"x": 0,
		"y": 0,
		"z": 0
	},
	"IsGroupPosition": false,
	"GroupPositions": [],
	"Root": "5e382a0e285547152560389a",
	"Items": [
		{
			"_id": "5e382a0e285547152560389a",
			"_tpl": "5909d76c86f77471e53d2adf"
		},
		{
			"_id": "5e382a0e285547152560389b",
			"_tpl": "58272d7f2459774f6311ddfd",
			"parentId": "5e382a0e285547152560389a",
			"slotId": "main",
			"location": {
				"x": 0,
				"y": 0,
				"r": 0
			}
		},
		{
			"_id": "5e382a0e285547152560389c",
			"_tpl": "59db3b0886f77429d72fb895",
			"parentId": "5e382a0e285547152560389a",
			"slotId": "main",
			"location": {
				"x": 1,
				"y": 0,
				"r": 0
			}
		},
		{
			"_id": "5e382a0e285547152560389d",
			"_tpl": "570fd6c2d2720bc6458b457f",
			"parentId": "5e382a0e285547152560389a",
			"slotId": "main",
			"location": {
				"x": 2,
				"y": 0,
				"r": 0
			}
		}
	]
}