{
	"items": [
		{
			"_id": "5c6687d65e9d882c8841f0fd",
			"_tpl": "55d7217a4bdc2d86028b456d"
		},
		{
			"_id": "5c6687d65e9d882c8841f121",
			"_tpl": "557ffd194bdc2d28148b457f",
			"parentId": "5c6687d65e9d882c8841f0fd",
			"slotId": "Pockets"
		},
		{
			"_id": "5c6687d65e9d882c8841f0fc",
			"_tpl": "566abbc34bdc2d92178b4576"
		},
		{
			"_id": "5c6687d65e9d882c8841f0ff",
			"_tpl": "5963866b86f7747bfa1c4462"
		},
		{
			"_id": "5c6687d65e9d882c8841f0fe",
			"_tpl": "5963866286f7747bf429b572"
		},
		{
			"_id": "TacticalVest895515",
			"_tpl": "592c2d1a86f7746dbe2af32a",
			"parentId": "5c6687d65e9d882c8841f0fd",
			"slotId": "TacticalVest"
		},
		{
			"_id": "I210839111791020511hIVCN",
			"_tpl": "5bb2475ed4351e00853264e3",
			"parentId": "5c6687d65e9d882c8841f0fd",
			"slotId": "FirstPrimaryWeapon"
		},
		{
			"_id": "I210839115286148835eXiwU",
			"_tpl": "5c6d7b3d2e221600114c9b7d",
			"parentId": "I210839111791020511hIVCN",
			"slotId": "mod_pistol_grip"
		},
		{
			"_id": "MagazineWeaponScav1",
			"_tpl": "5aaa5dfee5b5b000140293d3",
			"parentId": "I210839111791020511hIVCN",
			"slotId": "mod_magazine"
		},
		{
			"_id": "AmmoMag12806",
			"_tpl": "59e68f6f86f7746c9f75e846",
			"parentId": "MagazineWeaponScav1",
			"slotId": "cartridges",
			"upd": {
				"StackObjectsCount": 30
			}
		},
		{
			"_id": "I2108391166361310919tqzl",
			"_tpl": "5bb20d53d4351e4502010a69",
			"parentId": "I210839111791020511hIVCN",
			"slotId": "mod_reciever"
		},
		{
			"_id": "I210839112478982268ddReb",
			"_tpl": "5947eab886f77475961d96c5",
			"parentId": "I210839111791020511hIVCN",
			"slotId": "mod_stock"
		},
		{
			"_id": "I2108391122490738236gzVb",
			"_tpl": "5d44334ba4b9362b346d1948",
			"parentId": "I210839111791020511hIVCN",
			"slotId": "mod_charge"
		},
		{
			"_id": "I210839114875654001V62Iz",
			"_tpl": "5c6d85e02e22165df16b81f4",
			"parentId": "I2108391166361310919tqzl",
			"slotId": "mod_barrel"
		},
		{
			"_id": "I210839114577718754oMguE",
			"_tpl": "5bb20de5d4351e0035629e59",
			"parentId": "I2108391166361310919tqzl",
			"slotId": "mod_handguard"
		},
		{
			"_id": "I210839119334190165z15v0",
			"_tpl": "5c18b9192e2216398b5a8104",
			"parentId": "I2108391166361310919tqzl",
			"slotId": "mod_sight_rear",
			"upd": {
				"Sight": {
					"SelectedSightMode": 0
				}
			}
		},
		{
			"_id": "I210839114778483051n1k7t",
			"_tpl": "5cc9b815d7f00c000e2579d6",
			"parentId": "I210839114875654001V62Iz",
			"slotId": "mod_muzzle"
		},
		{
			"_id": "I210839118289192166scnaD",
			"_tpl": "5bb20dcad4351e3bac1212da",
			"parentId": "I210839114875654001V62Iz",
			"slotId": "mod_gas_block"
		},
		{
			"_id": "I210839111166671819NheIh",
			"_tpl": "58c157be86f77403c74b2bb6",
			"parentId": "I210839114577718754oMguE",
			"slotId": "mod_foregrip"
		},
		{
			"_id": "I2108391131224937824Ky2c",
			"_tpl": "5c18b90d2e2216152142466b",
			"parentId": "I210839114577718754oMguE",
			"slotId": "mod_sight_front",
			"upd": {
				"Sight": {
					"SelectedSightMode": 0
				}
			}
		},
		{
			"_id": "I2108391199691121448jHc3",
			"_tpl": "544909bb4bdc2d6f028b4577",
			"parentId": "I210839114577718754oMguE",
			"slotId": "mod_tactical_001",
			"upd": {
				"Light": {
					"IsActive": true,
					"SelectedMode": 0
				}
			}
		},
		{
			"_id": "mag0Vest268833",
			"_tpl": "5aaa5dfee5b5b000140293d3",
			"parentId": "TacticalVest895515",
			"slotId": "5",
			"location": {
				"x": 0,
				"y": 0,
				"r": "Horizontal"
			}
		},
		{
			"_id": "AmmoMag0Vest800459",
			"_tpl": "59e68f6f86f7746c9f75e846",
			"parentId": "mag0Vest268833",
			"slotId": "cartridges",
			"upd": {
				"StackObjectsCount": 30
			}
		},
		{
			"_id": "mag0Vest105257",
			"_tpl": "5aaa5dfee5b5b000140293d3",
			"parentId": "TacticalVest895515",
			"slotId": "6",
			"location": {
				"x": 1,
				"y": 0,
				"r": "Horizontal"
			}
		},
		{
			"_id": "AmmoMag0Vest627864",
			"_tpl": "5c0d5ae286f7741e46554302",
			"parentId": "mag0Vest105257",
			"slotId": "cartridges",
			"upd": {
				"StackObjectsCount": 30
			}
		},
		{
			"_id": "Scabbard935401",
			"_tpl": "5c0116620db834001808a647",
			"parentId": "5c6687d65e9d882c8841f0fd",
			"slotId": "Scabbard"
		},
		{
			"_id": "Headwear10151",
			"_tpl": "5aa7cfc0e5b5b00015693143",
			"parentId": "5c6687d65e9d882c8841f0fd",
			"slotId": "Headwear"
		},
		{
			"_id": "FaceCover827899",
			"_tpl": "572b7f1624597762ae139822",
			"parentId": "5c6687d65e9d882c8841f0fd",
			"slotId": "FaceCover"
		},
		{
			"_id": "Backpack576356",
			"_tpl": "56e335e4d2720b6c058b456d",
			"parentId": "5c6687d65e9d882c8841f0fd",
			"slotId": "Backpack"
		},
		{
			"_id": "BP_Backpack576356_134245",
			"_tpl": "59fc48e086f77463b1118392",
			"parentId": "Backpack576356",
			"slotId": "main",
			"location": {
				"x": 0,
				"y": 0,
				"r": "Horizontal"
			}
		},
		{
			"_id": "BP_Backpack576356_741091",
			"_tpl": "5addc7db5acfc4001669f279",
			"parentId": "Backpack576356",
			"slotId": "main",
			"location": {
				"x": 0,
				"y": 1,
				"r": "Horizontal"
			}
		},
		{
			"_id": "BP_Backpack576356_752708",
			"_tpl": "5913611c86f77479e0084092",
			"parentId": "Backpack576356",
			"slotId": "main",
			"location": {
				"x": 0,
				"y": 2,
				"r": "Horizontal"
			}
		},
		{
			"_id": "ArmorVest786352",
			"_tpl": "5c0e625a86f7742d77340f62",
			"parentId": "5c6687d65e9d882c8841f0fd",
			"slotId": "ArmorVest",
			"upd": {
				"Repairable": {
					"MaxDurability": 75,
					"Durability": 50
				}
			}
		},
		{
			"_id": "Pocket_886120",
			"_tpl": "590a3c0a86f774385a33c450",
			"parentId": "5c6687d65e9d882c8841f121",
			"slotId": "pocket1",
			"location": {
				"x": 0,
				"y": 0,
				"r": "Horizontal"
			},
			"upd": {
				"SpawnedInSession": true
			}
		},
		{
			"_id": "Pocket_603386",
			"_tpl": "5ad5d7d286f77450166e0a89",
			"parentId": "5c6687d65e9d882c8841f121",
			"slotId": "pocket2",
			"location": {
				"x": 0,
				"y": 0,
				"r": "Horizontal"
			},
			"upd": {
				"SpawnedInSession": true
			}
		}
	],
	"equipment": "5c6687d65e9d882c8841f0fd",
	"stash": "5c6687d65e9d882c8841f0fc",
	"questRaidItems": "5c6687d65e9d882c8841f0fe",
	"questStashItems": "5c6687d65e9d882c8841f0ff",
	"fastPanel": {}
}