{
	"items": [
		{
			"_id": "5c6687d65e9d882c8841f0fd",
			"_tpl": "55d7217a4bdc2d86028b456d"
		},
		{
			"_id": "5c6687d65e9d882c8841f121",
			"_tpl": "557ffd194bdc2d28148b457f",
			"parentId": "5c6687d65e9d882c8841f0fd",
			"slotId": "Pockets"
		},
		{
			"_id": "5c6687d65e9d882c8841f0fc",
			"_tpl": "566abbc34bdc2d92178b4576"
		},
		{
			"_id": "5c6687d65e9d882c8841f0ff",
			"_tpl": "5963866b86f7747bfa1c4462"
		},
		{
			"_id": "5c6687d65e9d882c8841f0fe",
			"_tpl": "5963866286f7747bf429b572"
		},
		{
			"_id": "TacticalVest300595",
			"_tpl": "5b44cad286f77402a54ae7e5",
			"parentId": "5c6687d65e9d882c8841f0fd",
			"slotId": "TacticalVest"
		},
		{
			"_id": "I072248569264204484hRkCw",
			"_tpl": "5926bb2186f7744b1c6c6e60",
			"parentId": "5c6687d65e9d882c8841f0fd",
			"slotId": "FirstPrimaryWeapon"
		},
		{
			"_id": "MagazineWeaponScav4305",
			"_tpl": "5d2f213448f0355009199284",
			"parentId": "I072248569264204484hRkCw",
			"slotId": "mod_magazine"
		},
		{
			"_id": "AmmoMag16747",
			"_tpl": "5c3df7d588a4501f290594e5",
			"parentId": "MagazineWeaponScav4305",
			"slotId": "cartridges",
			"upd": {
				"StackObjectsCount": 20
			}
		},
		{
			"_id": "I072248564299491797GJ77V",
			"_tpl": "5926c0df86f77462f647f764",
			"parentId": "I072248569264204484hRkCw",
			"slotId": "mod_reciever",
			"upd": {
				"SpawnedInSession": true
			}
		},
		{
			"_id": "I072248562280787569NE4aC",
			"_tpl": "5926c32286f774616e42de99",
			"parentId": "I072248569264204484hRkCw",
			"slotId": "mod_charge",
			"upd": {
				"SpawnedInSession": true
			}
		},
		{
			"_id": "I072248566954358652VGXhp",
			"_tpl": "5a9548c9159bd400133e97b3",
			"parentId": "I072248564299491797GJ77V",
			"slotId": "mod_handguard",
			"upd": {
				"SpawnedInSession": true
			}
		},
		{
			"_id": "I072248564550879176AHYSN",
			"_tpl": "5926d3c686f77410de68ebc8",
			"parentId": "I072248564299491797GJ77V",
			"slotId": "mod_stock",
			"upd": {
				"SpawnedInSession": true
			}
		},
		{
			"_id": "I072248563209391665k3daU",
			"_tpl": "5c0000c00db834001a6697fc",
			"parentId": "I072248564299491797GJ77V",
			"slotId": "mod_muzzle",
			"upd": {
				"SpawnedInSession": true
			}
		},
		{
			"_id": "I072248569329715792sXDlm",
			"_tpl": "5a966ec8a2750c00171b3f36",
			"parentId": "I072248564299491797GJ77V",
			"slotId": "mod_mount",
			"upd": {
				"SpawnedInSession": true
			}
		},
		{
			"_id": "I072248564411773469lk416",
			"_tpl": "5b057b4f5acfc4771e1bd3e9",
			"parentId": "I072248566954358652VGXhp",
			"slotId": "mod_foregrip",
			"upd": {
				"SpawnedInSession": true
			}
		},
		{
			"_id": "I072248561746008419IGZ1h",
			"_tpl": "5cc9c20cd7f00c001336c65d",
			"parentId": "I072248566954358652VGXhp",
			"slotId": "mod_tactical_000",
			"upd": {
				"SpawnedInSession": true
			}
		},
		{
			"_id": "I072248562549317397V0raz",
			"_tpl": "5c6165902e22160010261b28",
			"parentId": "I072248563209391665k3daU",
			"slotId": "mod_muzzle",
			"upd": {
				"SpawnedInSession": true
			}
		},
		{
			"_id": "I072248565729564084QUmKG",
			"_tpl": "5d2da1e948f035477b1ce2ba",
			"parentId": "I072248569329715792sXDlm",
			"slotId": "mod_scope",
			"upd": {
				"SpawnedInSession": true
			}
		},
		{
			"_id": "I07224912907477550zSa1xc",
			"_tpl": "5cc9c20cd7f00c001336c65d",
			"parentId": "I072248566954358652VGXhp",
			"slotId": "mod_tactical_001",
			"upd": {
				"SpawnedInSession": true
			}
		},
		{
			"_id": "mag0Vest109577",
			"_tpl": "5d2f213448f0355009199284",
			"parentId": "TacticalVest300595",
			"slotId": "1",
			"location": {
				"x": 0,
				"y": 0,
				"r": "Horizontal"
			}
		},
		{
			"_id": "AmmoMag0Vest784161",
			"_tpl": "56d59d3ad2720bdb418b4577",
			"parentId": "mag0Vest109577",
			"slotId": "cartridges",
			"upd": {
				"StackObjectsCount": 20
			}
		},
		{
			"_id": "mag0Vest216548",
			"_tpl": "5d2f213448f0355009199284",
			"parentId": "TacticalVest300595",
			"slotId": "1",
			"location": {
				"x": 0,
				"y": 1,
				"r": "Horizontal"
			}
		},
		{
			"_id": "AmmoMag0Vest813256",
			"_tpl": "5a3c16fe86f77452b62de32a",
			"parentId": "mag0Vest216548",
			"slotId": "cartridges",
			"upd": {
				"StackObjectsCount": 20
			}
		},
		{
			"_id": "mag1Vest721275",
			"_tpl": "5d2f213448f0355009199284",
			"parentId": "TacticalVest300595",
			"slotId": "3",
			"location": {
				"x": 0,
				"y": 0,
				"r": "Horizontal"
			}
		},
		{
			"_id": "AmmoMag1Vest686539",
			"_tpl": "58864a4f2459770fcc257101",
			"parentId": "mag1Vest721275",
			"slotId": "cartridges",
			"upd": {
				"StackObjectsCount": 20
			}
		},
		{
			"_id": "mag1Vest953365",
			"_tpl": "5d2f213448f0355009199284",
			"parentId": "TacticalVest300595",
			"slotId": "3",
			"location": {
				"x": 0,
				"y": 1,
				"r": "Horizontal"
			}
		},
		{
			"_id": "AmmoMag1Vest790488",
			"_tpl": "5c0d56a986f774449d5de529",
			"parentId": "mag1Vest953365",
			"slotId": "cartridges",
			"upd": {
				"StackObjectsCount": 20
			}
		},
		{
			"_id": "mag3Vest558826",
			"_tpl": "5d2f213448f0355009199284",
			"parentId": "TacticalVest300595",
			"slotId": "12",
			"location": {
				"x": 0,
				"y": 1,
				"r": "Horizontal"
			}
		},
		{
			"_id": "AmmoMag3Vest274695",
			"_tpl": "5c0d56a986f774449d5de529",
			"parentId": "mag3Vest558826",
			"slotId": "cartridges",
			"upd": {
				"StackObjectsCount": 20
			}
		},
		{
			"_id": "Scabbard146581",
			"_tpl": "5bffdc370db834001d23eca8",
			"parentId": "5c6687d65e9d882c8841f0fd",
			"slotId": "Scabbard"
		},
		{
			"_id": "Headwear230482",
			"_tpl": "5e00c1ad86f774747333222c",
			"parentId": "5c6687d65e9d882c8841f0fd",
			"slotId": "Headwear"
		},
		{
			"_id": "Eyewear372281",
			"_tpl": "5c0d32fcd174af02a1659c75",
			"parentId": "5c6687d65e9d882c8841f0fd",
			"slotId": "Eyewear"
		},
		{
			"_id": "ArmorVest936707",
			"_tpl": "59e7635f86f7742cbf2c1095",
			"parentId": "5c6687d65e9d882c8841f0fd",
			"slotId": "ArmorVest",
			"upd": {
				"Repairable": {
					"MaxDurability": 40,
					"Durability": 21
				}
			}
		}
	],
	"equipment": "5c6687d65e9d882c8841f0fd",
	"stash": "5c6687d65e9d882c8841f0fc",
	"questRaidItems": "5c6687d65e9d882c8841f0fe",
	"questStashItems": "5c6687d65e9d882c8841f0ff",
	"fastPanel": {}
}