{
	"items": [
		{
			"_id": "5c6687d65e9d882c8841f0fd",
			"_tpl": "55d7217a4bdc2d86028b456d"
		},
		{
			"_id": "5c6687d65e9d882c8841f121",
			"_tpl": "557ffd194bdc2d28148b457f",
			"parentId": "5c6687d65e9d882c8841f0fd",
			"slotId": "Pockets"
		},
		{
			"_id": "5c6687d65e9d882c8841f0fc",
			"_tpl": "566abbc34bdc2d92178b4576"
		},
		{
			"_id": "5c6687d65e9d882c8841f0ff",
			"_tpl": "5963866b86f7747bfa1c4462"
		},
		{
			"_id": "5c6687d65e9d882c8841f0fe",
			"_tpl": "5963866286f7747bf429b572"
		},
		{
			"_id": "TacticalVest6149",
			"_tpl": "5648a69d4bdc2ded0b8b457b",
			"parentId": "5c6687d65e9d882c8841f0fd",
			"slotId": "TacticalVest"
		},
		{
			"_id": "I210059399066286350NLAGJ",
			"_tpl": "59e6152586f77473dc057aa1",
			"parentId": "5c6687d65e9d882c8841f0fd",
			"slotId": "FirstPrimaryWeapon"
		},
		{
			"_id": "I210059391805118847Ym4yc",
			"_tpl": "59e649f986f77411d949b246",
			"parentId": "I210059399066286350NLAGJ",
			"slotId": "mod_gas_block"
		},
		{
			"_id": "I210059399838498149cliHf",
			"_tpl": "59e61eb386f77440d64f5daf",
			"parentId": "I210059399066286350NLAGJ",
			"slotId": "mod_muzzle"
		},
		{
			"_id": "I210059394360360246mZw89",
			"_tpl": "59e6318286f77444dd62c4cc",
			"parentId": "I210059399066286350NLAGJ",
			"slotId": "mod_pistol_grip"
		},
		{
			"_id": "I210059399685113964yjREY",
			"_tpl": "59e6449086f7746c9f75e822",
			"parentId": "I210059399066286350NLAGJ",
			"slotId": "mod_reciever"
		},
		{
			"_id": "I21005939348550353263PQ6",
			"_tpl": "59d650cf86f7741b846413a4",
			"parentId": "I210059399066286350NLAGJ",
			"slotId": "mod_sight_rear",
			"upd": {
				"Sight": {
					"SelectedSightMode": 0
				}
			}
		},
		{
			"_id": "I210059399843345353YDKE1",
			"_tpl": "59e6284f86f77440d569536f",
			"parentId": "I210059391805118847Ym4yc",
			"slotId": "mod_handguard"
		},
		{
			"_id": "mag0Vest802427",
			"_tpl": "5ac66bea5acfc43b321d4aec",
			"parentId": "TacticalVest6149",
			"slotId": "1",
			"location": {
				"x": 0,
				"y": 0,
				"r": "Horizontal"
			}
		},
		{
			"_id": "AmmoMag0Vest801472",
			"_tpl": "59e4d3d286f774176a36250a",
			"parentId": "mag0Vest802427",
			"slotId": "cartridges",
			"upd": {
				"StackObjectsCount": 30
			}
		},
		{
			"_id": "mag2Vest189823",
			"_tpl": "5ac66bea5acfc43b321d4aec",
			"parentId": "TacticalVest6149",
			"slotId": "4",
			"location": {
				"x": 0,
				"y": 0,
				"r": "Horizontal"
			}
		},
		{
			"_id": "AmmoMag2Vest118506",
			"_tpl": "59e4cf5286f7741778269d8a",
			"parentId": "mag2Vest189823",
			"slotId": "cartridges",
			"upd": {
				"StackObjectsCount": 30
			}
		},
		{
			"_id": "mag0Vest839280",
			"_tpl": "5ac66bea5acfc43b321d4aec",
			"parentId": "TacticalVest6149",
			"slotId": "5",
			"location": {
				"x": 1,
				"y": 0,
				"r": "Horizontal"
			}
		},
		{
			"_id": "AmmoMag0Vest386485",
			"_tpl": "59e4d24686f7741776641ac7",
			"parentId": "mag0Vest839280",
			"slotId": "cartridges",
			"upd": {
				"StackObjectsCount": 30
			}
		},
		{
			"_id": "StackAmmo64558169682",
			"_tpl": "59e4d3d286f774176a36250a",
			"parentId": "TacticalVest6149",
			"slotId": "6",
			"upd": {
				"StackObjectsCount": 30
			}
		},
		{
			"_id": "Scabbard928521",
			"_tpl": "54491bb74bdc2d09088b4567",
			"parentId": "5c6687d65e9d882c8841f0fd",
			"slotId": "Scabbard"
		},
		{
			"_id": "Headwear213226",
			"_tpl": "572b7d8524597762b472f9d1",
			"parentId": "5c6687d65e9d882c8841f0fd",
			"slotId": "Headwear"
		},
		{
			"_id": "Eyewear104975",
			"_tpl": "5d5fca1ea4b93635fd598c07",
			"parentId": "5c6687d65e9d882c8841f0fd",
			"slotId": "Eyewear"
		},
		{
			"_id": "FaceCover143234",
			"_tpl": "572b7f1624597762ae139822",
			"parentId": "5c6687d65e9d882c8841f0fd",
			"slotId": "FaceCover"
		},
		{
			"_id": "Pocket_818531",
			"_tpl": "590a3b0486f7743954552bdb",
			"parentId": "5c6687d65e9d882c8841f121",
			"slotId": "pocket1",
			"location": {
				"x": 0,
				"y": 0,
				"r": "Horizontal"
			},
			"upd": {
				"SpawnedInSession": true
			}
		},
		{
			"_id": "Pocket_147835",
			"_tpl": "590c2b4386f77425357b6123",
			"parentId": "5c6687d65e9d882c8841f121",
			"slotId": "pocket2",
			"location": {
				"x": 0,
				"y": 0,
				"r": "Horizontal"
			},
			"upd": {
				"SpawnedInSession": true
			}
		}
	],
	"equipment": "5c6687d65e9d882c8841f0fd",
	"stash": "5c6687d65e9d882c8841f0fc",
	"questRaidItems": "5c6687d65e9d882c8841f0fe",
	"questStashItems": "5c6687d65e9d882c8841f0ff",
	"fastPanel": {}
}