{
	"items": [
		{
			"_id": "5c6687d65e9d882c8841f0fd",
			"_tpl": "55d7217a4bdc2d86028b456d"
		},
		{
			"_id": "5c6687d65e9d882c8841f121",
			"_tpl": "557ffd194bdc2d28148b457f",
			"parentId": "5c6687d65e9d882c8841f0fd",
			"slotId": "Pockets"
		},
		{
			"_id": "5c6687d65e9d882c8841f0fc",
			"_tpl": "566abbc34bdc2d92178b4576"
		},
		{
			"_id": "5c6687d65e9d882c8841f0ff",
			"_tpl": "5963866b86f7747bfa1c4462"
		},
		{
			"_id": "5c6687d65e9d882c8841f0fe",
			"_tpl": "5963866286f7747bf429b572"
		},
		{
			"_id": "TacticalVest444909",
			"_tpl": "5e4abfed86f77406a2713cf7",
			"parentId": "5c6687d65e9d882c8841f0fd",
			"slotId": "TacticalVest"
		},
		{
			"_id": "I210049337428853527kmWNO",
			"_tpl": "5a0ec13bfcdbcb00165aa685",
			"parentId": "5c6687d65e9d882c8841f0fd",
			"slotId": "FirstPrimaryWeapon"
		},
		{
			"_id": "I210049331249444390LODOt",
			"_tpl": "59d64ec286f774171d1e0a42",
			"parentId": "I210049337428853527kmWNO",
			"slotId": "mod_gas_block"
		},
		{
			"_id": "I210049333834946701ebAUj",
			"_tpl": "59d64fc686f774171b243fe2",
			"parentId": "I210049337428853527kmWNO",
			"slotId": "mod_muzzle"
		},
		{
			"_id": "I210049331187558035paNc2",
			"_tpl": "59e62cc886f77440d40b52a1",
			"parentId": "I210049337428853527kmWNO",
			"slotId": "mod_pistol_grip"
		},
		{
			"_id": "I210049334447998954DgA41",
			"_tpl": "59d6507c86f7741b846413a2",
			"parentId": "I210049337428853527kmWNO",
			"slotId": "mod_reciever"
		},
		{
			"_id": "I210049331494089981RGlbg",
			"_tpl": "59d650cf86f7741b846413a4",
			"parentId": "I210049337428853527kmWNO",
			"slotId": "mod_sight_rear",
			"upd": {
				"Sight": {
					"SelectedSightMode": 0
				}
			}
		},
		{
			"_id": "I210049338297097927alfHG",
			"_tpl": "59d64f2f86f77417193ef8b3",
			"parentId": "I210049331249444390LODOt",
			"slotId": "mod_handguard"
		},
		{
			"_id": "Scabbard785722",
			"_tpl": "5bffdc370db834001d23eca8",
			"parentId": "5c6687d65e9d882c8841f0fd",
			"slotId": "Scabbard"
		},
		{
			"_id": "Eyewear450178",
			"_tpl": "59e770b986f7742cbd762754",
			"parentId": "5c6687d65e9d882c8841f0fd",
			"slotId": "Eyewear"
		},
		{
			"_id": "FaceCover933892",
			"_tpl": "5bd0716d86f774171822ef4b",
			"parentId": "5c6687d65e9d882c8841f0fd",
			"slotId": "FaceCover"
		},
		{
			"_id": "Backpack151744",
			"_tpl": "544a5cde4bdc2d39388b456b",
			"parentId": "5c6687d65e9d882c8841f0fd",
			"slotId": "Backpack"
		},
		{
			"_id": "Pocket_291088",
			"_tpl": "5734773724597737fd047c14",
			"parentId": "5c6687d65e9d882c8841f121",
			"slotId": "pocket1",
			"location": {
				"x": 0,
				"y": 0,
				"r": "Horizontal"
			},
			"upd": {
				"SpawnedInSession": true
			}
		},
		{
			"_id": "Pocket_612887",
			"_tpl": "5734795124597738002c6176",
			"parentId": "5c6687d65e9d882c8841f121",
			"slotId": "pocket2",
			"location": {
				"x": 0,
				"y": 0,
				"r": "Horizontal"
			},
			"upd": {
				"SpawnedInSession": true
			}
		}
	],
	"equipment": "5c6687d65e9d882c8841f0fd",
	"stash": "5c6687d65e9d882c8841f0fc",
	"questRaidItems": "5c6687d65e9d882c8841f0fe",
	"questStashItems": "5c6687d65e9d882c8841f0ff",
	"fastPanel": {}
}