{
	"Id": "Lootable_00074",
	"IsStatic": true,
	"useGravity": true,
	"randomRotation": false,
	"Position": {
		"x": 0,
		"y": 0,
		"z": 0
	},
	"Rotation": {
		"x": 0,
		"y": 0,
		"z": 0
	},
	"IsGroupPosition": false,
	"GroupPositions": [],
	"Root": "5dd2955886f774793d4cd0ff",
	"Items": [
		{
			"_id": "5dd2955886f774793d4cd0ff",
			"_tpl": "578f87a3245977356274f2cb"
		},
		{
			"_id": "5dd2955886f774793d4cd100",
			"_tpl": "5751435d24597720a27126d1",
			"parentId": "5dd2955886f774793d4cd0ff",
			"slotId": "main",
			"location": {
				"x": 0,
				"y": 0,
				"r": 0
			}
		},
		{
			"_id": "5dd2955886f774793d4cd101",
			"_tpl": "5734773724597737fd047c14",
			"parentId": "5dd2955886f774793d4cd0ff",
			"slotId": "main",
			"location": {
				"x": 1,
				"y": 0,
				"r": 0
			}
		},
		{
			"_id": "5dd2955886f774793d4cd102",
			"_tpl": "573476d324597737da2adc13",
			"parentId": "5dd2955886f774793d4cd0ff",
			"slotId": "main",
			"location": {
				"x": 2,
				"y": 0,
				"r": 0
			}
		}
	]
}